Workbook

Sheet README
A1: Seasonal Agriculture Performance Analysis
A2: VOIS AICTE Batch1 2026-2027 — Major Project (Excel phase)
A4: Dataset: seasonal_agriculture_performance_dataset.csv — 4,000 farm records | 8 states | 8 crops | 3 seasons (Kharif, Rabi, Zaid)
A6: How this workbook is organised
A7: Sheet | B7: What's in it
A8: Raw_Data | B8: The original dataset, unedited (4,000 rows).
A9: Cleaning_Reference | B9: Per-crop yield quartiles used for imputing/capping outliers.
A10: Cleaned_Data | B10: Live formulas: missing values imputed, outliers capped, with flag columns showing what was changed.
A11: Data_Dictionary | B11: Column definitions and a plain-English summary of the cleaning steps.
A12: Season_Summary | B12: The core pivot-style table — ~23 metrics compared across Kharif / Rabi / Zaid.
A13: Season_Crop_Matrix | B13: Average yield and profit for each crop, broken down by season.
A14: Season_State_Matrix | B14: Average yield for each state, broken down by season (regional consistency check).
A15: Irrigation_Analysis | B15: Farm counts and water efficiency by irrigation method and season.
A16: Correlation_Analysis | B16: Pearson correlation coefficients between key variables and yield/profit.
A17: Charts | B17: Visualisations of the above (bar, pie, scatter) — all linked live to the data.
A18: Key_Insights_Recommendations | B18: Written findings mapped to the project's key questions, plus recommendations.
A20: Method note
A21: All summary/matrix/correlation figures are Excel formulas (AVERAGEIFS, SUMIFS, COUNTIFS, CORREL, INDEX/MATCH) referencing Cleaned_Data — nothing is hardcoded, so the workbook recalculates if the raw data changes. The next phase of this project (Python / Jupyter Notebook) will go deeper: statistical tests, per-season correlation, regression and richer visualisation.

Sheet Data_Dictionary
A1: Data Dictionary
A2: Field descriptions for the Seasonal Agriculture Performance dataset (4,000 farm records, 8 states, 8 crops, 3 seasons).
A4: Column | B4: Description
A5: Farm_ID | B5: Unique identifier for each farm record
A6: State | B6: Indian state where the farm is located (8 states)
A7: District | B7: District within the state
A8: Crop | B8: Crop cultivated (8 crop types)
A9: Season | B9: Cropping season: Kharif (monsoon), Rabi (winter), Zaid (summer)
A10: Farm_Area_Hectares | B10: Total cultivated area of the farm, in hectares
A11: Rainfall_mm | B11: Total rainfall received during the season, in millimetres
A12: Avg_Temperature_C | B12: Average temperature during the season, in Celsius
A13: Humidity_pct | B13: Average relative humidity, in percent
A14: Sunlight_Hours_Day | B14: Average sunlight hours per day
A15: Soil_pH | B15: Soil pH level (acidity/alkalinity)
... A32: Disease_Pest_Risk_pct | B32: Estimated disease/pest risk score, percent
A35: Cleaning Methodology (see Cleaned_Data sheet)
A36: 1. Missing Rainfall_mm (48 records) imputed with the season average.
A37: 2. Missing Soil_Moisture_pct (40 records) imputed with the season average.
A38: 3. Missing Yield_Tonnes_Ha (32 records) imputed with the Season x Crop average.
A39: 4. Yield outliers capped at the crop's IQR upper bound (Q3 + 1.5xIQR); see Cleaning_Reference sheet.
A40: 5. Production_Recalculated_t recomputes production from the cleaned yield x farm area for consistency.
A41: 6. No duplicate Farm_ID values were found in the raw dataset.

Sheet Raw_Data
A1: Farm_ID | B1: State | C1: District | D1: Crop | E1: Season | F1: Farm_Area_Hectares | G1: Rainfall_mm | H1: Avg_Temperature_C | I1: Humidity_pct | J1: Sunlight_Hours_Day | K1: Soil_pH | L1: Soil_Moisture_pct | M1: Nitrogen_kg_ha | N1: Phosphorus_kg_ha | O1: Potassium_kg_ha | P1: Irrigation_Method | Q1: Fertilizer_kg_ha | R1: Pesticide_Litre_ha | S1: Seed_Quality_Score | T1: Yield_Tonnes_Ha | U1: Production_Tonnes | V1: Market_Price_INR_Tonne | W1: Total_Cost_INR | X1: Revenue_INR | Y1: Profit_INR | Z1: Water_Used_m3 | AA1: Water_Efficiency_t_per_1000m3 | AB1: Disease_Pest_Risk_pct
A2: SF10001 | B2: Andhra Pradesh | C2: Rajkot | D2: Wheat | E2: Kharif | F2: 0.53 | G2: 486.4 | H2: 24.3 | I2: 69.1 | J2: 5.8 | K2: 7.14 | L2: 32.8 | M2: 75.8 | N2: 61.3 | O2: 91 | P2: Drip | Q2: 242.7 | R2: 4.33 | S2: 0.76 | T2: 2.46 | U2: 1.3 | V2: 23700 | W2: 42662 | X2: 30810 | Y2: -11852 | Z2: 237 | AA2: 5.485 | AB2: 55.3
A3: SF10002 | B3: Maharashtra | C3: Nalgonda | D3: Maize | E3: Kharif | F3: 6.53 | G3: 855.4 | H3: 25.7 | I3: 78.4 | J3: 5.1 | K3: 5.2 | L3: 32 | M3: 82.1 | N3: 35.4 | O3: 121.8 | P3: Flood | Q3: 271.4 | R3: 6.86 | S3: 0.94 | T3: 0.3 | U3: 1.96 | V3: 20613 | W3: 492351 | X3: 40401 | Y3: -451950 | Z3: 4953 | AA3: 0.396 | AB3: 49.9
A4: SF10003 | B4: Telangana | C4: Warangal | D4: Pulses | E4: Rabi | F4: 4.86 | G4: 455.6 | H4: 23.9 | I4: 56.4 | J4: 10.3 | K4: 5.82 | L4: 8.1 | M4: 118.5 | N4: 51.5 | O4: 117.9 | P4: Drip | Q4: 162.6 | R4: 6.08 | S4: 0.98 | T4: 0.52 | U4: 2.53 | V4: 75283 | W4: 315210 | X4: 190466 | Y4: -124744 | Z4: 1275 | AA4: 1.984 | AB4: 33.7
A5: SF10004 | B5: Telangana | C5: Indore | D5: Rice | E5: Kharif | F5: 4.5 | G5: 753.2 | H5: 29.7 | I5: 65.2 | J5: 6.3 | K5: 5.98 | L5: 23.7 | M5: 138.6 | N5: 55.6 | O5: 115.5 | P5: Rainfed | Q5: 182.2 | R5: 6.39 | S5: 0.74 | T5: 1.84 | U5: 8.28 | V5: 24244 | W5: 296444 | X5: 200740 | Y5: -95704 | Z5: 3834 | AA5: 2.16 | AB5: 50.6
A6: SF10005 | B6: Karnataka | C6: Ludhiana | D6: Maize | E6: Zaid | F6: 4.21 | G6: 101.6 | H6: 34.1 | I6: 55.2 | J6: 6.5 | K6: 6.9 | L6: 29.3 | M6: 124.1 | N6: 69 | O6: 121.4 | P6: Flood | Q6: 244.9 | R6: 7.61 | S6: 0.9 | T6: 2.21 | U6: 9.3 | V6: 20818 | W6: 337959 | X6: 193607 | Y6: -144352 | Z6: 3287 | AA6: 2.829 | AB6: 32.3
A7: SF10006 | B7: Gujarat | C7: Raichur | D7: Pulses | E7: Zaid | F7: 5.46 | G7: 356 | H7: 33.6 | I7: 49 | J7: 8.3 | K7: 6.93 | L7: 11.4 | M7: 105.1 | N7: 34.7 | O7: 78.7 | P7: Rainfed | Q7: 58.8 | R7: 4.48 | S7: 0.89 | T7: 0.72 | U7: 3.93 | V7: 68593 | W7: 302333 | X7: 269570 | Y7: -32763 | Z7: 1093 | AA7: 3.596 | AB7: 57.1
A8: SF10007 | B8: Telangana | C8: Warangal | D8: Wheat | E8: Rabi | F8: 8.13 | G8: 432.2 | H8: 23.5 | I8: 50.8 | J8: 9.5 | K8: 6.96 | L8: 24.7 | M8: 115.8 | N8: 69.4 | O8: 109.8 | P8: Rainfed | Q8: 181.6 | R8: 7.99 | S8: 0.87 | T8: 2.53 | U8: 20.57 | V8: 22951 | W8: 513341 | X8: 472102 | Y8: -41239 | Z8: 2368 | AA8: 8.687 | AB8: 31.6
A9: SF10008 | B9: Tamil Nadu | C9: Ludhiana | D9: Pulses | E9: Kharif | F9: 5.34 | G9: 860.2 | H9: 29 | I9: 64.9 | J9: 7.9 | K9: 6.09 | L9: 36.9 | M9: 112.7 | N9: 60.9 | O9: 115.9 | P9: Sprinkler | Q9: 245.8 | R9: 5.89 | S9: 0.7 | T9: 1.18 | U9: 6.3 | V9: 70042 | W9: 436200 | X9: 441265 | Y9: 5065 | Z9: 1704 | AA9: 3.697 | AB9: 54.2
A10: SF10009 | B10: Karnataka | C10: Guntur | D10: Cotton | E10: Zaid | F10: 6.98 | G10: 624.7 | H10: 33.4 | I10: 46.8 | J10: 7.9 | K10: 6.41 | L10: 12.3 | M10: 66.9 | N10: 47.6 | O10: 134.2 | P10: Sprinkler | Q10: 190.7 | R10: 2.21 | S10: 0.88 | T10: 1.53 | U10: 10.68 | V10: 70771 | W10: 525129 | X10: 755834 | Y10: 230705 | Z10: 5079 | AA10: 2.103 | AB10: 54.7
A11: SF10010 | B11: Tamil Nadu | C11: Raichur | D11: Chilli | E11: Rabi | F11: 13.69 | G11: 415.8 | H11: 22.3 | I11: 57.3 | J11: 8.6 | K11: 6.6 | L11: 23.3 | M11: 117.9 | N11: 37.2 | O11: 116.6 | P11: Drip | Q11: 168.8 | R11: 7.29 | S11: 0.7 | T11: 2.29 | U11: 31.35 | V11: 94383 | W11: 1004072 | X11: 2958907 | Y11: 1954835 | Z11: 5984 | AA11: 5.239 | AB11: 41.7
A12: SF10011 | B12: Maharashtra | C12: Krishna | D12: Wheat | E12: Rabi | F12: 4.7 | G12: 390.8 | H12: 24.5 | I12: 43.5 | J12: 7.8 | K12: 5.93 | L12: 25.2 | M12: 137.9 | N12: 31.4 | O12: 70 | P12: Sprinkler | Q12: 224.4 | R12: 5.9 | S12: 0.89 | T12: 1.44 | U12: 6.77 | V12: 20806 | W12: 289759 | X12: 140857 | Y12: -148902 | Z12: 2371 | AA12: 2.855 | AB12: 33.5
A13: SF10012 | B13: Telangana | C13: Rajkot | D13: Maize | E13: Rabi | F13: 14.07 | G13: 315.3 | H13: 24.2 | I13: 53.7 | J13: 5.9 | K13: 5.87 | L13: 29.4 | M13: 100.6 | N13: 50.8 | O13: 65.8 | P13: Drip | Q13: 178.7 | R13: 5.34 | S13: 0.71 | T13: 1.36 | U13: 19.14 | V13: 20120 | W13: 964512 | X13: 385097 | Y13: -579415 | Z13: 7467 | AA13: 2.563 | AB13: 35
... A29: SF10028 | B29: Punjab | C29: Rajkot | D29: Rice | E29: Rabi | F29: 10.47 | G29: 93.9 | H29: 27.3 | I29: 45.4 | J29: 7.7 | K29: 6.89 | L29: 27 | M29: 115.6 | N29: 64.9 | O29: 123.2 | P29: Rainfed | Q29: 210.2 | R29: 2.42 | S29: 0.74 | T29: 2.45 | U29: 25.65 | V29: 21364 | W29: 545453 | X29: 547987 | Y29: 2534 | Z29: 9077 | AA29: 2.826 | AB29: 45.7
A30: SF10029 | B30: Tamil Nadu | C30: Rajkot | D30: Maize | E30: Rabi | F30: 12.94 | G30: 443.1 | H30: 23 | I30: 45.7 | J30: 6.3 | K30: 6.32 | M30: 139.3 | N30: 51.3 | O30: 92.5 | P30: Sprinkler | Q30: 286.7 | R30: 8.22 | S30: 0.97 | T30: 3.01 | U30: 38.95 | V30: 20272 | W30: 1176978 | X30: 789594 | Y30: -387384 | Z30: 8230 | AA30: 4.733 | AB30: 32.1
A31: SF10030 | B31: Tamil Nadu | C31: Rajkot | D31: Groundnut | E31: Zaid | F31: 13.15 | G31: 565.4 | H31: 32.7 | I31: 50.7 | J31: 7.3 | K31: 6.65 | L31: 15.6 | M31: 158 | N31: 46.8 | O31: 151 | P31: Sprinkler | Q31: 147.4 | R31: 5.5 | S31: 0.89 | T31: 1.94 | U31: 25.51 | V31: 49492 | W31: 695563 | X31: 1262541 | Y31: 566978 | Z31: 7423 | AA31: 3.437 | AB31: 30.6
A32: SF10031 | B32: Telangana | C32: Nalgonda | D32: Chilli | E32: Rabi | F32: 11.96 | G32: 284.2 | H32: 24.1 | I32: 62.1 | J32: 7 | K32: 6.93 | L32: 31.7 | M32: 188.8 | N32: 47.8 | O32: 101.6 | P32: Rainfed | Q32: 250.8 | R32: 4.06 | S32: 0.66 | T32: 1.51 | U32: 18.06 | V32: 102219 | W32: 738746 | X32: 1846075 | Y32: 1107329 | Z32: 4721 | AA32: 3.825 | AB32: 40.2
A33: SF10032 | B33: Madhya Pradesh | C33: Krishna | D33: Groundnut | E33: Zaid | F33: 0.69 | G33: 372.1 | H33: 31.7 | I33: 30.8 | J33: 7.4 | K33: 7.92 | L33: 12.2 | M33: 127.3 | N33: 66.2 | O33: 131.1 | P33: Drip | Q33: 139.4 | R33: 4.39 | S33: 0.96 | T33: 0.3 | U33: 0.21 | V33: 54155 | W33: 43431 | X33: 11373 | Y33: -32058 | Z33: 259 | AA33: 0.811 | AB33: 37.4
A34: SF10033 | B34: Madhya Pradesh | C34: Indore | D34: Cotton | E34: Kharif | F34: 11.35 | G34: 1066.8 | H34: 30.3 | I34: 76.6 | J34: 6.4 | K34: 7.56 | L34: 35.9 | M34: 104.2 | N34: 49.9 | O34: 106.8 | P34: Sprinkler | Q34: 230.7 | R34: 4.16 | S34: 0.7 | T34: 0.64 | U34: 7.26 | V34: 72112 | W34: 782371 | X34: 523533 | Y34: -258838 | Z34: 9585 | AA34: 0.757 | AB34: 67.7
A35: SF10034 | B35: Andhra Pradesh | C35: Guntur | D35: Maize | E35: Kharif | F35: 9.8 | G35: 849 | H35: 26.4 | I35: 88 | J35: 8.2 | K35: 6.03 | L35: 35.5 | M35: 154.3 | N35: 49.1 | O35: 129.8 | P35: Sprinkler | Q35: 220.2 | R35: 4.34 | S35: 0.72 | T35: 3.65 | U35: 35.77 | V35: 21914 | W35: 782502 | X35: 783864 | Y35: 1362 | Z35: 5884 | AA35: 6.079 | AB35: 52.1
A36: SF10035 | B36: Madhya Pradesh | C36: Ludhiana | D36: Wheat | E36: Rabi | F36: 11.57 | G36: 427.5 | H36: 24 | I36: 59.3 | J36: 6.7 | K36: 6.71 | L36: 28.5 | M36: 157.3 | N36: 71.5 | O36: 84.3 | P36: Sprinkler | Q36: 186.8 | R36: 1.13 | S36: 0.86 | T36: 3.83 | U36: 44.31 | V36: 26126 | W36: 648827 | X36: 1157643 | Y36: 508816 | Z36: 5400 | AA36: 8.206 | AB36: 61.4
A37: SF10036 | B37: Madhya Pradesh | C37: Indore | D37: Cotton | E37: Zaid | F37: 7.05 | G37: 179.4 | H37: 34.1 | I37: 55.5 | J37: 8.7 | K37: 7 | L37: 14.8 | M37: 94.3 | N37: 66.8 | O37: 101.3 | P37: Flood | Q37: 231.5 | R37: 7.26 | S37: 0.96 | T37: 0.75 | U37: 5.29 | V37: 66996 | W37: 511293 | X37: 354409 | Y37: -156884 | Z37: 5944 | AA37: 0.89 | AB37: 29
A38: SF10037 | B38: Tamil Nadu | C38: Nalgonda | D38: Cotton | E38: Rabi | F38: 3.11 | G38: 429.3 | H38: 23.6 | I38: 60.1 | J38: 7.9 | K38: 6.96 | L38: 20.7 | M38: 40 | N38: 73.9 | O38: 114.2 | P38: Drip | Q38: 229 | R38: 6.96 | S38: 0.68 | T38: 1.71 | U38: 5.32 | V38: 52396 | W38: 243775 | X38: 278747 | Y38: 34972 | Z38: 1780 | AA38: 2.989 | AB38: 33
A39: SF10038 | B39: Andhra Pradesh | C39: Ludhiana | D39: Cotton | E39: Kharif | F39: 2.79 | G39: 820.1 | H39: 26.3 | I39: 74.6 | J39: 7.5 | K39: 7.62 | L39: 31.9 | M39: 123.2 | N39: 91.7 | O39: 80.6 | P39: Flood | Q39: 153.2 | R39: 5.91 | S39: 0.68 | T39: 0.7 | U39: 1.95 | V39: 66405 | W39: 175756 | X39: 129490 | Y39: -46266 | Z39: 3058 | AA39: 0.638 | AB39: 52.5
A40: SF10039 | B40: Telangana | C40: Warangal | D40: Wheat | E40: Kharif | F40: 4.69 | G40: 657.7 | H40: 27.1 | I40: 64.9 | J40: 6.2 | K40: 7.85 | L40: 31.9 | M40: 87.6 | N40: 87.5 | O40: 81.5 | P40: Drip | Q40: 218.9 | R40: 4.78 | S40: 0.92 | T40: 0.98 | U40: 4.6 | V40: 25408 | W40: 293568 | X40: 116877 | Y40: -176691 | Z40: 2392 | AA40: 1.923 | AB40: 50
A41: SF10040 | B41: Tamil Nadu | C41: Ludhiana | D41: Maize | E41: Kharif | F41: 6.12 | G41: 936 | H41: 31.8 | I41: 56.3 | J41: 7.1 | K41: 7.03 | L41: 30.3 | M41: 91.9 | N41: 48 | O41: 103.6 | P41: Rainfed | Q41: 46.3 | R41: 8.07 | S41: 0.79 | T41: 3.24 | U41: 19.83 | V41: 24731 | W41: 321710 | X41: 490416 | Y41: 168706 | Z41: 2144 | AA41: 9.249 | AB41: 46.7
A42: SF10041 | B42: Karnataka | C42: Indore | D42: Pulses | E42: Kharif | F42: 12.31 | G42: 768.4 | H42: 29 | I42: 67 | J42: 6.1 | K42: 8.22 | L42: 26.7 | M42: 69.5 | N42: 49.1 | O42: 98.6 | P42: Flood | Q42: 214.2 | R42: 7.11 | S42: 0.73 | T42: 0.3 | U42: 3.69 | V42: 95238 | W42: 791517 | X42: 351428 | Y42: -440089 | Z42: 6153 | AA42: 0.6 | AB42: 54.7
... A44: SF10043 | B44: Karnataka | C44: Krishna | D44: Rice | E44: Kharif | F44: 9.47 | G44: 639.2 | H44: 22.6 | I44: 74.9 | J44: 4.9 | K44: 5.73 | L44: 43.6 | M44: 66.1 | N44: 54.9 | O44: 125.5 | P44: Rainfed | Q44: 313.4 | R44: 4.78 | S44: 0.94 | T44: 0.9 | U44: 8.52 | V44: 25346 | W44: 744619 | X44: 215948 | Y44: -528671 | Z44: 7926 | AA44: 1.075 | AB44: 52
A45: SF10044 | B45: Tamil Nadu | C45: Erode | D45: Wheat | E45: Rabi | F45: 7.56 | G45: 460.1 | H45: 24 | I45: 58.7 | J45: 6.7 | K45: 6.6 | M45: 96.2 | N45: 42.9 | O45: 139.3 | P45: Sprinkler | Q45: 241.9 | R45: 5.34 | S45: 0.69 | T45: 2.6 | U45: 19.66 | V45: 24887 | W45: 550176 | X45: 489278 | Y45: -60898 | Z45: 4545 | AA45: 4.326 | AB45: 44.7
A46: SF10045 | B46: Madhya Pradesh | C46: Krishna | D46: Wheat | E46: Kharif | F46: 14.23 | G46: 853.7 | H46: 28.2 | I46: 77.6 | J46: 6.9 | K46: 7.04 | L46: 31.8 | M46: 109.5 | N46: 61.7 | O46: 148.7 | P46: Drip | Q46: 163.7 | R46: 4.26 | S46: 0.85 | T46: 3.35 | U46: 47.67 | V46: 23547 | W46: 980255 | X46: 1122485 | Y46: 142230 | Z46: 5966 | AA46: 7.99 | AB46: 55.4
A47: SF10046 | B47: Telangana | C47: Erode | D47: Wheat | E47: Kharif | F47: 2.14 | G47: 485.7 | H47: 28 | I47: 80.1 | J47: 7.2 | K47: 8.08 | L47: 34.7 | M47: 111 | N47: 56.6 | O47: 74.9 | P47: Drip | Q47: 146.2 | R47: 4.25 | S47: 0.95 | T47: 0.32 | U47: 0.68 | V47: 25224 | W47: 116463 | X47: 17152 | Y47: -99311 | Z47: 791 | AA47: 0.86 | AB47: 49.4
A48: SF10047 | B48: Andhra Pradesh | C48: Nalgonda | D48: Groundnut | E48: Kharif | F48: 5.6 | G48: 728.5 | H48: 27 | I48: 76.7 | J48: 6.9 | K48: 6.36 | L48: 27.4 | M48: 92.2 | N48: 72.7 | O48: 80.9 | P48: Sprinkler | Q48: 194 | R48: 4.7 | S48: 0.71 | T48: 2.63 | U48: 14.73 | V48: 53568 | W48: 337133 | X48: 789057 | Y48: 451924 | Z48: 3052 | AA48: 4.826 | AB48: 63.2
A49: SF10048 | B49: Punjab | C49: Ludhiana | D49: Sugarcane | E49: Zaid | F49: 7.68 | G49: 90 | H49: 31.9 | I49: 52.7 | J49: 9.8 | K49: 6.51 | L49: 18.3 | M49: 164 | N49: 59.6 | O49: 54.9 | P49: Sprinkler | Q49: 136.9 | R49: 8.04 | S49: 0.76 | T49: 36.69 | U49: 281.78 | V49: 3682 | W49: 480826 | X49: 1037514 | Y49: 556688 | Z49: 13263 | AA49: 21.246 | AB49: 30
A50: SF10049 | B50: Andhra Pradesh | C50: Erode | D50: Chilli | E50: Zaid | F50: 5.52 | G50: 91.3 | H50: 34.1 | I50: 63 | J50: 7.2 | K50: 5.55 | L50: 20.9 | M50: 124.8 | N50: 75.2 | O50: 130.8 | P50: Rainfed | Q50: 207.3 | R50: 4.96 | S50: 0.87 | T50: 0.3 | U50: 1.66 | V50: 102697 | W50: 376564 | X50: 170477 | Y50: -206087 | Z50: 1257 | AA50: 1.321 | AB50: 43.9
A51: SF10050 | B51: Madhya Pradesh | C51: Erode | D51: Rice | E51: Rabi | F51: 8.8 | G51: 792.2 | H51: 21.5 | I51: 51.4 | J51: 8 | K51: 7.8 | L51: 21.8 | M51: 104.1 | N51: 61.9 | O51: 82.3 | P51: Flood | Q51: 223.7 | R51: 6.7 | S51: 0.7 | T51: 0.76 | U51: 6.69 | V51: 19703 | W51: 741670 | X51: 131813 | Y51: -609857 | Z51: 15881 | AA51: 0.421 | AB51: 53.6
A52: SF10051 | B52: Telangana | C52: Warangal | D52: Rice | E52: Zaid | F52: 9.82 | G52: 227.2 | H52: 29.5 | I52: 63.5 | J52: 7.6 | K52: 6.81 | L52: 17.8 | M52: 122.5 | N52: 54.9 | O52: 97 | P52: Flood | Q52: 162.7 | R52: 0.62 | S52: 0.78 | T52: 2.87 | U52: 28.18 | V52: 21316 | W52: 534995 | X52: 600685 | Y52: 65690 | Z52: 16682 | AA52: 1.689 | AB52: 49.4
A53: SF10052 | B53: Andhra Pradesh | C53: Rajkot | D53: Pulses | E53: Rabi | F53: 8.61 | G53: 80 | H53: 24.8 | I53: 60.9 | J53: 7.5 | K53: 5.43 | L53: 28 | M53: 107.1 | N53: 46.4 | O53: 137.6 | P53: Sprinkler | Q53: 178.1 | R53: 4.92 | S53: 1 | T53: 0.3 | U53: 2.58 | V53: 71065 | W53: 492155 | X53: 183348 | Y53: -308807 | Z53: 3106 | AA53: 0.831 | AB53: 40.2
A54: SF10053 | B54: Gujarat | C54: Indore | D54: Rice | E54: Zaid | F54: 11.52 | G54: 206.2 | H54: 34.3 | I54: 50.3 | J54: 10 | K54: 7.01 | L54: 32.7 | M54: 106.7 | N54: 50.4 | O54: 98.1 | P54: Flood | Q54: 112.7 | R54: 6.15 | S54: 0.87 | T54: 1.69 | U54: 19.47 | V54: 19275 | W54: 674473 | X54: 375284 | Y54: -299189 | Z54: 20211 | AA54: 0.963 | AB54: 18.9
A55: SF10054 | B55: Telangana | C55: Nalgonda | D55: Maize | E55: Kharif | F55: 3.18 | G55: 591.2 | H55: 28.1 | I55: 63.9 | J55: 6.8 | K55: 5.66 | L55: 30.8 | M55: 126.9 | N55: 27.6 | O55: 137.7 | P55: Flood | Q55: 289.5 | R55: 5.4 | S55: 0.77 | T55: 1.11 | U55: 3.53 | V55: 17359 | W55: 254223 | X55: 61277 | Y55: -192946 | Z55: 2327 | AA55: 1.517 | AB55: 39.8
A56: SF10055 | B56: Andhra Pradesh | C56: Raichur | D56: Rice | E56: Rabi | F56: 7.08 | G56: 460 | H56: 22.8 | I56: 57.4 | J56: 8.5 | K56: 7.14 | L56: 19.2 | M56: 125.2 | N56: 30.8 | O56: 126.7 | P56: Flood | Q56: 115.3 | R56: 6.38 | S56: 0.94 | T56: 2.92 | U56: 20.67 | V56: 24229 | W56: 591425 | X56: 500813 | Y56: -90612 | Z56: 16012 | AA56: 1.291 | AB56: 29.2
A57: SF10056 | B57: Karnataka | C57: Warangal | D57: Groundnut | E57: Rabi | F57: 11.7 | G57: 167.3 | H57: 26.2 | I57: 62.4 | J57: 6.8 | K57: 6.3 | L57: 21.8 | M57: 122.8 | N57: 27.7 | O57: 135 | P57: Drip | Q57: 240.5 | R57: 5.39 | S57: 0.94 | U57: 19.42 | V57: 50837 | W57: 780159 | X57: 987255 | Y57: 207096 | Z57: 4665 | AA57: 4.163 | AB57: 39.4
A58: SF10057 | B58: Telangana | C58: Nashik | D58: Pulses | E58: Rabi | F58: 6.91 | G58: 489.4 | H58: 24 | I58: 67.2 | J58: 9.1 | K58: 6.46 | L58: 31 | M58: 121.2 | N58: 55.7 | O58: 107.5 | P58: Drip | Q58: 212 | R58: 6.15 | S58: 0.87 | T58: 1.49 | U58: 10.3 | V58: 70845 | W58: 462116 | X58: 729704 | Y58: 267588 | Z58: 2165 | AA58: 4.758 | AB58: 34.5
A59: SF10058 | B59: Telangana | C59: Nashik | D59: Maize | E59: Zaid | F59: 7.06 | G59: 336.9 | H59: 29.4 | I59: 62 | J59: 9 | K59: 7.53 | L59: 11.3 | M59: 152.4 | N59: 63.1 | O59: 106.1 | P59: Rainfed | Q59: 116.8 | R59: 4.01 | S59: 0.86 | T59: 1.16 | U59: 8.19 | V59: 22633 | W59: 430059 | X59: 185364 | Y59: -244695 | Z59: 2031 | AA59: 4.032 | AB59: 33.3
A60: SF10059 | B60: Madhya Pradesh | C60: Raichur | D60: Maize | E60: Zaid | F60: 6.62 | G60: 278.1 | H60: 31.1 | I60: 59.3 | J60: 8.3 | K60: 7.55 | L60: 19.1 | M60: 129.3 | N60: 82 | O60: 47 | P60: Flood | Q60: 168 | R60: 2.1 | S60: 0.89 | T60: 1.34 | U60: 8.87 | V60: 18651 | W60: 455124 | X60: 165434 | Y60: -289690 | Z60: 5550 | AA60: 1.598 | AB60: 47.6
A61: SF10060 | B61: Gujarat | C61: Erode | D61: Groundnut | E61: Kharif | F61: 10 | G61: 664.7 | H61: 25.1 | I61: 72.3 | J61: 6.8 | K61: 6.49 | L61: 32.8 | M61: 118.6 | N61: 31.3 | O61: 69.5 | P61: Flood | Q61: 139.1 | R61: 5.53 | S61: 0.76 | T61: 2.07 | U61: 20.7 | V61: 59223 | W61: 619756 | X61: 1225916 | Y61: 606160 | Z61: 7146 | AA61: 2.897 | AB61: 42.2
A62: SF10061 | B62: Karnataka | C62: Guntur | D62: Groundnut | E62: Kharif | F62: 14.38 | G62: 1002 | H62: 27.9 | I62: 63 | J62: 5.5 | K62: 6.62 | L62: 30.2 | M62: 127.4 | N62: 61.8 | O62: 86.2 | P62: Rainfed | Q62: 194.4 | R62: 5.01 | S62: 0.97 | T62: 1.73 | U62: 24.88 | V62: 53834 | W62: 972766 | X62: 1339390 | Y62: 366624 | Z62: 4408 | AA62: 5.644 | AB62: 66.6
A63: SF10062 | B63: Karnataka | C63: Ludhiana | D63: Cotton | E63: Rabi | F63: 14.23 | G63: 404.4 | H63: 19.4 | I63: 55.8 | J63: 7.9 | K63: 6.99 | L63: 22.6 | M63: 182 | N63: 52.9 | O63: 80.5 | P63: Drip | Q63: 127.2 | R63: 1.21 | S63: 0.9 | T63: 1.8 | U63: 25.61 | V63: 70385 | W63: 815920 | X63: 1802560 | Y63: 986640 | Z63: 9798 | AA63: 2.614 | AB63: 50.7
A64: SF10063 | B64: Andhra Pradesh | C64: Warangal | D64: Cotton | E64: Zaid | F64: 5.46 | G64: 148.5 | H64: 31.2 | I64: 59.9 | J64: 7.7 | K64: 6.31 | L64: 21.5 | M64: 81.9 | N64: 56 | O64: 124.3 | P64: Flood | Q64: 157.7 | R64: 3.34 | S64: 0.7 | T64: 0.91 | U64: 4.97 | V64: 66056 | W64: 309945 | X64: 328298 | Y64: 18353 | Z64: 4831 | AA64: 1.029 | AB64: 31.8
A65: SF10064 | B65: Tamil Nadu | C65: Warangal | D65: Rice | E65: Kharif | F65: 3.95 | G65: 1028.8 | H65: 24.2 | I65: 69.2 | J65: 6.2 | K65: 5.95 | L65: 29.4 | M65: 105.4 | N65: 48.3 | O65: 123.3 | P65: Flood | Q65: 136.3 | R65: 4.4 | S65: 0.92 | T65: 1.62 | U65: 6.4 | V65: 23591 | W65: 258728 | X65: 150982 | Y65: -107746 | Z65: 8230 | AA65: 0.778 | AB65: 46.8
A66: SF10065 | B66: Telangana | C66: Indore | D66: Pulses | E66: Kharif | F66: 14.43 | G66: 1012.7 | H66: 30.2 | I66: 65.2 | J66: 7.9 | K66: 6.71 | L66: 23.2 | M66: 102.9 | N66: 66.6 | O66: 93.5 | P66: Rainfed | Q66: 276.7 | R66: 5.63 | S66: 0.97 | T66: 0.99 | U66: 14.29 | V66: 86381 | W66: 980375 | X66: 1234384 | Y66: 254009 | Z66: 2290 | AA66: 6.24 | AB66: 53.6
A67: SF10066 | B67: Maharashtra | C67: Rajkot | D67: Groundnut | E67: Rabi | F67: 7.49 | G67: 234.8 | H67: 20.5 | I67: 49.1 | J67: 8.4 | K67: 6.55 | L67: 30.3 | M67: 84.7 | N67: 72.9 | O67: 72.2 | P67: Sprinkler | Q67: 107.5 | R67: 3.99 | S67: 0.82 | T67: 1.42 | U67: 10.64 | V67: 60410 | W67: 506733 | X67: 642762 | Y67: 136029 | Z67: 3460 | AA67: 3.075 | AB67: 59.9
A68: SF10067 | B68: Tamil Nadu | C68: Rajkot | D68: Wheat | E68: Rabi | F68: 7.25 | G68: 410 | H68: 23.4 | I68: 61.1 | J68: 9.4 | K68: 7.08 | L68: 28.3 | M68: 199.3 | N68: 60.4 | O68: 66.8 | P68: Flood | Q68: 198.1 | R68: 7.33 | S68: 0.8 | T68: 2.66 | U68: 19.28 | V68: 20402 | W68: 542011 | X68: 393351 | Y68: -148660 | Z68: 4731 | AA68: 4.075 | AB68: 41.4
A69: SF10068 | B69: Maharashtra | C69: Ludhiana | D69: Pulses | E69: Rabi | F69: 5.28 | G69: 498.8 | H69: 26.9 | I69: 51.3 | J69: 7.5 | K69: 6.21 | L69: 29 | M69: 152.6 | N69: 48.9 | O69: 95.2 | P69: Drip | Q69: 114.7 | R69: 5.33 | S69: 0.69 | T69: 1.37 | U69: 7.23 | V69: 71305 | W69: 292198 | X69: 515535 | Y69: 223337 | Z69: 1540 | AA69: 4.695 | AB69: 44.1
... A122: SF10121 | B122: Gujarat | C122: Rajkot | D122: Groundnut | E122: Kharif | F122: 11.46 | G122: 619.1 | H122: 24.5 | I122: 83.3 | J122: 6.6 | K122: 6.71 | L122: 30.4 | M122: 84.1 | N122: 46.5 | O122: 113.3 | P122: Rainfed | Q122: 184.4 | R122: 4.84 | S122: 0.84 | T122: 2.07 | U122: 23.72 | V122: 65653 | W122: 811732 | X122: 1557289 | Y122: 745557 | Z122: 2898 | AA122: 8.185 | AB122: 60.2
A123: SF10122 | B123: Maharashtra | C123: Erode | D123: Cotton | E123: Kharif | F123: 3.26 | G123: 896.1 | H123: 34.8 | I123: 69.5 | J123: 7.2 | K123: 5.55 | M123: 63.3 | N123: 59.8 | O123: 144.8 | P123: Sprinkler | Q123: 164.3 | R123: 4.67 | S123: 0.98 | T123: 0.3 | U123: 0.98 | V123: 57631 | W123: 193353 | X123: 56478 | Y123: -136875 | Z123: 2439 | AA123: 0.402 | AB123: 51.3
A124: SF10123 | B124: Madhya Pradesh | C124: Warangal | D124: Rice | E124: Rabi | F124: 4.65 | G124: 227.6 | H124: 24.9 | I124: 55.9 | J124: 6.8 | K124: 7.8 | L124: 26.3 | M124: 97.5 | N124: 96.6 | O124: 97 | P124: Flood | Q124: 162.3 | R124: 3.82 | S124: 0.95 | T124: 0.66 | U124: 3.07 | V124: 26404 | W124: 294129 | X124: 81060 | Y124: -213069 | Z124: 8874 | AA124: 0.346 | AB124: 36.6
A125: SF10124 | B125: Punjab | C125: Indore | D125: Pulses | E125: Kharif | F125: 2.54 | G125: 499.7 | H125: 29.6 | I125: 76.4 | J125: 7.2 | K125: 7.74 | L125: 30.7 | M125: 112.7 | N125: 42.4 | O125: 125 | P125: Drip | Q125: 201.3 | R125: 4.02 | S125: 0.97 | T125: 0.4 | U125: 1.02 | V125: 73000 | W125: 182833 | X125: 74460 | Y125: -108373 | Z125: 895 | AA125: 1.14 | AB125: 51.3
A126: SF10125 | B126: Madhya Pradesh | C126: Rajkot | D126: Pulses | E126: Kharif | F126: 14.46 | G126: 763.3 | H126: 32.5 | I126: 77 | J126: 6.3 | K126: 7.23 | L126: 27.2 | M126: 158.4 | N126: 51.1 | O126: 56.6 | P126: Rainfed | Q126: 206.5 | R126: 4.14 | S126: 0.97 | T126: 0.78 | U126: 11.28 | V126: 79479 | W126: 1012756 | X126: 896523 | Y126: -116233 | Z126: 2927 | AA126: 3.854 | AB126: 65.4
A127: SF10126 | B127: Maharashtra | C127: Nalgonda | D127: Chilli | E127: Rabi | F127: 8.45 | G127: 575.8 | H127: 24.3 | I127: 57.8 | J127: 7.5 | K127: 7.02 | L127: 18.5 | M127: 115.2 | N127: 67.5 | O127: 125 | P127: Sprinkler | Q127: 197.3 | R127: 4.51 | S127: 0.93 | T127: 2.34 | U127: 19.77 | V127: 90018 | W127: 532885 | X127: 1779656 | Y127: 1246771 | Z127: 5842 | AA127: 3.384 | AB127: 57.1
A128: SF10127 | B128: Telangana | C128: Guntur | D128: Wheat | E128: Rabi | F128: 3.75 | G128: 99.6 | H128: 27.2 | I128: 56.7 | J128: 6.8 | K128: 6.08 | L128: 26.1 | M128: 160.8 | N128: 66.3 | O128: 46.8 | P128: Rainfed | Q128: 101.6 | R128: 4.45 | S128: 0.97 | T128: 1.6 | U128: 6 | V128: 23135 | W128: 192862 | X128: 138810 | Y128: -54052 | Z128: 1165 | AA128: 5.15 | AB128: 41.7
A129: SF10128 | B129: Tamil Nadu | C129: Erode | D129: Wheat | E129: Rabi | F129: 11.28 | G129: 281.9 | H129: 23.4 | I129: 69.3 | J129: 7.4 | K129: 6.62 | L129: 27.2 | M129: 154.3 | N129: 28.4 | O129: 95.3 | P129: Rainfed | Q129: 154.9 | R129: 5.89 | S129: 0.68 | T129: 2.24 | U129: 25.27 | V129: 27337 | W129: 702245 | X129: 690806 | Y129: -11439 | Z129: 3065 | AA129: 8.245 | AB129: 31
A130: SF10129 | B130: Maharashtra | C130: Raichur | D130: Maize | E130: Rabi | F130: 10.33 | G130: 606.2 | H130: 21.7 | I130: 46.6 | J130: 9.5 | K130: 6.73 | L130: 33.2 | M130: 121.8 | N130: 60.8 | O130: 92.8 | P130: Drip | Q130: 166.9 | R130: 3.5 | S130: 0.84 | T130: 4.89 | U130: 50.51 | V130: 19769 | W130: 685674 | X130: 998532 | Y130: 312858 | Z130: 5130 | AA130: 9.846 | AB130: 48.8
A131: SF10130 | B131: Maharashtra | C131: Nalgonda | D131: Pulses | E131: Rabi | F131: 3.95 | G131: 296 | H131: 23.2 | I131: 68.3 | J131: 8.3 | K131: 6.93 | L131: 17 | M131: 77 | N131: 76.7 | O131: 68.9 | P131: Sprinkler | Q131: 114.9 | R131: 9.35 | S131: 0.74 | T131: 1.01 | U131: 3.99 | V131: 86219 | W131: 272305 | X131: 344014 | Y131: 71709 | Z131: 1545 | AA131: 2.583 | AB131: 22.2
A132: SF10131 | B132: Tamil Nadu | C132: Nalgonda | D132: Wheat | E132: Kharif | F132: 4.55 | G132: 759.9 | H132: 26.9 | I132: 78 | J132: 8.1 | K132: 6.17 | L132: 32.2 | M132: 115.5 | N132: 63.7 | O132: 55.6 | P132: Flood | Q132: 127 | R132: 5.57 | S132: 0.91 | T132: 2.73 | U132: 12.42 | V132: 23075 | W132: 292455 | X132: 286592 | Y132: -5863 | Z132: 3187 | AA132: 3.897 | AB132: 47
A133: SF10132 | B133: Karnataka | C133: Guntur | D133: Cotton | E133: Kharif | F133: 6.85 | G133: 1044.5 | H133: 26.3 | I133: 73.7 | J133: 7.1 | K133: 7.12 | L133: 31.5 | M133: 153.5 | N133: 70 | O133: 88.9 | P133: Sprinkler | Q133: 178.3 | R133: 4.87 | S133: 0.96 | T133: 1.86 | U133: 12.74 | V133: 67026 | W133: 398694 | X133: 853911 | Y133: 455217 | Z133: 5482 | AA133: 2.324 | AB133: 46.2
A134: SF10133 | B134: Telangana | C134: Warangal | D134: Sugarcane | E134: Kharif | F134: 3.83 | G134: 1158.2 | H134: 27.2 | I134: 68.4 | J134: 7 | K134: 7.4 | L134: 32.2 | M134: 84.3 | N134: 51.2 | O134: 95.2 | P134: Sprinkler | Q134: 252.4 | R134: 5.08 | S134: 0.82 | T134: 29.47 | U134: 112.87 | V134: 3123 | W134: 263380 | X134: 352493 | Y134: 89113 | Z134: 6337 | AA134: 17.811 | AB134: 53.9
A135: SF10134 | B135: Telangana | C135: Indore | D135: Chilli | E135: Rabi | F135: 5.69 | G135: 765.3 | H135: 22.2 | I135: 56.6 | J135: 7.4 | K135: 6.42 | L135: 21.5 | M135: 139.4 | N135: 72.6 | O135: 128.8 | P135: Flood | Q135: 227.4 | R135: 5.88 | S135: 0.87 | T135: 1.88 | U135: 10.7 | V135: 117774 | W135: 375375 | X135: 1260182 | Y135: 884807 | Z135: 5136 | AA135: 2.083 | AB135: 37.9
... A164: SF10163 | B164: Telangana | C164: Krishna | D164: Maize | E164: Zaid | F164: 1.58 | G164: 313.9 | H164: 27.7 | I164: 41.8 | J164: 9 | K164: 6.87 | L164: 16.5 | M164: 142.9 | N164: 59.9 | O164: 99.3 | P164: Sprinkler | Q164: 143.5 | R164: 8.86 | S164: 0.81 | T164: 3.69 | U164: 5.83 | V164: 20761 | W164: 121054 | X164: 121037 | Y164: -17 | Z164: 662 | AA164: 8.807 | AB164: 25.6
A165: SF10164 | B165: Madhya Pradesh | C165: Erode | D165: Pulses | E165: Zaid | F165: 3.55 | G165: 445.9 | H165: 29.7 | I165: 61.1 | J165: 8.2 | K165: 5.58 | L165: 20 | M165: 98.2 | N165: 25.5 | O165: 139.1 | P165: Flood | Q165: 194.7 | R165: 2.7 | S165: 0.89 | U165: 1.06 | V165: 58920 | W165: 206701 | X165: 62455 | Y165: -144246 | Z165: 1837 | AA165: 0.577 | AB165: 44.3
A166: SF10165 | B166: Telangana | C166: Guntur | D166: Sugarcane | E166: Rabi | F166: 4 | G166: 391.2 | H166: 25.6 | I166: 59.8 | J166: 8.7 | K166: 7.19 | L166: 21.8 | M166: 76.7 | N166: 74.6 | O166: 111.1 | P166: Rainfed | Q166: 189.6 | R166: 7.85 | S166: 0.67 | T166: 36.91 | U166: 147.64 | V166: 3771 | W166: 259517 | X166: 556750 | Y166: 297233 | Z166: 3618 | AA166: 40.807 | AB166: 24
A167: SF10166 | B167: Andhra Pradesh | C167: Erode | D167: Wheat | E167: Kharif | F167: 13.1 | G167: 795.3 | H167: 24.5 | I167: 55.5 | J167: 6.3 | K167: 8.34 | L167: 30.9 | M167: 124.8 | N167: 46.3 | O167: 149.8 | P167: Flood | Q167: 161.7 | R167: 7.08 | S167: 0.97 | T167: 0.3 | U167: 3.93 | V167: 21813 | W167: 871765 | X167: 85725 | Y167: -786040 | Z167: 10261 | AA167: 0.383 | AB167: 44.8
A168: SF10167 | B168: Maharashtra | C168: Warangal | D168: Chilli | E168: Kharif | F168: 14.99 | G168: 697.7 | H168: 27.4 | I168: 61.3 | J168: 6.5 | K168: 5.53 | L168: 26.2 | M168: 172.2 | N168: 76.6 | O168: 104.8 | P168: Sprinkler | Q168: 172.4 | R168: 5.59 | S168: 0.99 | T168: 0.7 | U168: 10.49 | V168: 102884 | W168: 940792 | X168: 1079253 | Y168: 138461 | Z168: 8999 | AA168: 1.166 | AB168: 48.6
A169: SF10168 | B169: Tamil Nadu | C169: Nashik | D169: Rice | E169: Rabi | F169: 8.43 | G169: 407.1 | H169: 21.3 | I169: 60.1 | J169: 8 | K169: 6.59 | L169: 24.4 | M169: 116.4 | N169: 70.6 | O169: 128.5 | P169: Flood | Q169: 301.1 | R169: 2.9 | S169: 0.98 | T169: 3.22 | U169: 27.14 | V169: 18202 | W169: 706137 | X169: 494002 | Y169: -212135 | Z169: 13146 | AA169: 2.065 | AB169: 33.7
A170: SF10169 | B170: Karnataka | C170: Erode | D170: Chilli | E170: Zaid | F170: 8.99 | G170: 142.5 | H170: 37.1 | I170: 65.7 | J170: 7.6 | K170: 6.47 | L170: 20 | M170: 104.1 | N170: 52.9 | O170: 124.6 | P170: Drip | Q170: 199.5 | R170: 7.2 | S170: 0.76 | T170: 1.19 | U170: 10.7 | V170: 116560 | W170: 644651 | X170: 1247192 | Y170: 602541 | Z170: 4758 | AA170: 2.249 | AB170: 33.9
A171: SF10170 | B171: Maharashtra | C171: Erode | D171: Cotton | E171: Rabi | F171: 4.65 | G171: 520 | H171: 20.1 | I171: 58.6 | J171: 8 | K171: 6.32 | L171: 31.3 | M171: 85.4 | N171: 85.2 | O171: 69.1 | P171: Drip | Q171: 69.1 | R171: 4.84 | S171: 0.89 | T171: 1.43 | U171: 6.65 | V171: 70386 | W171: 222809 | X171: 468067 | Y171: 245258 | Z171: 2992 | AA171: 2.223 | AB171: 42.7
A172: SF10171 | B172: Maharashtra | C172: Rajkot | D172: Maize | E172: Kharif | F172: 7.86 | G172: 699.2 | H172: 31.4 | I172: 73.3 | J172: 8.7 | K172: 6.71 | L172: 31.3 | M172: 113.7 | N172: 59.6 | O172: 117.1 | P172: Flood | Q172: 231.6 | R172: 3.08 | S172: 0.73 | T172: 4.2 | U172: 33.01 | V172: 20755 | W172: 430506 | X172: 685123 | Y172: 254617 | Z172: 6532 | AA172: 5.054 | AB172: 47.7
A173: SF10172 | B173: Punjab | C173: Warangal | D173: Groundnut | E173: Rabi | F173: 12.38 | G173: 542.7 | H173: 19.9 | I173: 61.5 | J173: 7 | K173: 6.5 | L173: 31.8 | M173: 87.3 | N173: 47.8 | O173: 144.1 | P173: Flood | Q173: 258 | R173: 3.65 | S173: 0.87 | T173: 1.54 | U173: 19.07 | V173: 53882 | W173: 963373 | X173: 1027530 | Y173: 64157 | Z173: 8914 | AA173: 2.139 | AB173: 39.5
A174: SF10173 | B174: Maharashtra | C174: Nashik | D174: Pulses | E174: Kharif | F174: 5.96 | G174: 621.6 | H174: 27.7 | I174: 76 | J174: 8.2 | K174: 6.8 | L174: 24.6 | M174: 111.3 | N174: 51.8 | O174: 111.1 | P174: Rainfed | Q174: 44.8 | R174: 0.65 | S174: 0.8 | T174: 1.47 | U174: 8.76 | V174: 67101 | W174: 213412 | X174: 587805 | Y174: 374393 | Z174: 1242 | AA174: 7.053 | AB174: 59.3
A175: SF10174 | B175: Gujarat | C175: Warangal | D175: Rice | E175: Rabi | F175: 4.76 | G175: 464.9 | H175: 21.6 | I175: 62.5 | J175: 8.1 | K175: 5.86 | L175: 20 | M175: 40 | N175: 58 | O175: 52.8 | P175: Flood | Q175: 191.3 | R175: 2.86 | S175: 0.96 | T175: 1.11 | U175: 5.28 | V175: 21916 | W175: 312302 | X175: 115716 | Y175: -196586 | Z175: 7861 | AA175: 0.672 | AB175: 46
A176: SF10175 | B176: Telangana | C176: Indore | D176: Wheat | E176: Kharif | F176: 2.03 | G176: 1085.5 | H176: 28.9 | I176: 77.9 | J176: 6.4 | K176: 6.69 | L176: 31.9 | M176: 156.5 | N176: 35.2 | O176: 111.4 | P176: Rainfed | Q176: 100.5 | R176: 5.38 | S176: 0.98 | T176: 3.21 | U176: 6.52 | V176: 23900 | W176: 127691 | X176: 155828 | Y176: 28137 | Z176: 577 | AA176: 11.3 | AB176: 63.9
A177: SF10176 | B177: Karnataka | C177: Guntur | D177: Pulses | E177: Zaid | F177: 2.53 | G177: 80 | H177: 34 | I177: 56.9 | J177: 8.8 | K177: 7.99 | L177: 22.8 | M177: 131 | N177: 39.9 | O177: 129.8 | P177: Flood | Q177: 262.9 | R177: 6.8 | S177: 0.99 | T177: 0.3 | U177: 0.76 | V177: 67343 | W177: 179667 | X177: 51181 | Y177: -128486 | Z177: 1363 | AA177: 0.558 | AB177: 35.4
... A187: SF10186 | B187: Maharashtra | C187: Guntur | D187: Rice | E187: Zaid | F187: 7.74 | G187: 271.1 | H187: 36 | I187: 49.9 | J187: 6.5 | K187: 7.22 | L187: 16.9 | M187: 112.5 | N187: 39 | O187: 152 | P187: Sprinkler | Q187: 137 | R187: 3.85 | S187: 0.95 | T187: 1.84 | U187: 14.24 | V187: 23621 | W187: 593150 | X187: 336363 | Y187: -256787 | Z187: 11788 | AA187: 1.208 | AB187: 42.9
A188: SF10187 | B188: Tamil Nadu | C188: Indore | D188: Rice | E188: Rabi | F188: 2.39 | H188: 21.3 | I188: 55.5 | J188: 8.4 | K188: 7.08 | L188: 30 | M188: 103.3 | N188: 53.4 | O188: 102.7 | P188: Flood | Q188: 177.5 | R188: 6.51 | S188: 0.77 | T188: 2.41 | U188: 5.76 | V188: 22588 | W188: 171055 | X188: 130107 | Y188: -40948 | Z188: 3882 | AA188: 1.484 | AB188: 43.3
A189: SF10188 | B189: Telangana | C189: Indore | D189: Wheat | E189: Kharif | F189: 1.44 | G189: 927.2 | H189: 27.3 | I189: 75.8 | J189: 7.2 | K189: 6.61 | L189: 36.9 | M189: 188.9 | N189: 61.6 | O189: 121.1 | P189: Drip | Q189: 215.6 | R189: 4.27 | S189: 0.74 | T189: 3.53 | U189: 5.08 | V189: 24563 | W189: 117305 | X189: 124780 | Y189: 7475 | Z189: 666 | AA189: 7.628 | AB189: 72.6
A190: SF10189 | B190: Madhya Pradesh | C190: Indore | D190: Pulses | E190: Rabi | F190: 5.67 | G190: 358.4 | H190: 25.1 | I190: 59.5 | J190: 7.5 | K190: 6.62 | L190: 30.1 | M190: 151.4 | N190: 39.8 | O190: 124.4 | P190: Drip | Q190: 184.6 | R190: 4.55 | S190: 0.81 | T190: 1.27 | U190: 7.2 | V190: 73052 | W190: 389581 | X190: 525974 | Y190: 136393 | Z190: 1597 | AA190: 4.508 | AB190: 40.6
A191: SF10190 | B191: Tamil Nadu | C191: Krishna | D191: Groundnut | E191: Kharif | F191: 2.04 | G191: 927 | H191: 27.7 | I191: 70.9 | J191: 5 | K191: 6.97 | L191: 31.8 | M191: 154.2 | N191: 68.9 | O191: 113.4 | P191: Flood | Q191: 257.7 | R191: 8.39 | S191: 0.67 | T191: 2.06 | U191: 4.2 | V191: 52915 | W191: 140715 | X191: 222243 | Y191: 81528 | Z191: 1093 | AA191: 3.843 | AB191: 43.9
A192: SF10191 | B192: Tamil Nadu | C192: Indore | D192: Chilli | E192: Kharif | F192: 2.16 | G192: 1068.9 | H192: 29.7 | I192: 73 | J192: 7.1 | K192: 6.97 | L192: 30.6 | M192: 148.9 | N192: 50.1 | O192: 126.2 | P192: Sprinkler | Q192: 308.3 | R192: 6.18 | S192: 0.83 | T192: 1.7 | U192: 3.67 | V192: 102163 | W192: 183052 | X192: 374938 | Y192: 191886 | Z192: 1427 | AA192: 2.572 | AB192: 60.7
A193: SF10192 | B193: Madhya Pradesh | C193: Rajkot | D193: Wheat | E193: Rabi | F193: 12.63 | G193: 275.6 | H193: 25.3 | I193: 59.8 | J193: 8.1 | K193: 6.75 | L193: 29.7 | M193: 93.9 | N193: 58.2 | O193: 76.2 | P193: Rainfed | Q193: 260.6 | R193: 6.26 | S193: 0.77 | T193: 2.09 | U193: 26.4 | V193: 27106 | W193: 850962 | X193: 715598 | Y193: -135364 | Z193: 3909 | AA193: 6.754 | AB193: 32.2
A194: SF10193 | B194: Maharashtra | C194: Ludhiana | D194: Rice | E194: Rabi | F194: 7.76 | G194: 432 | H194: 19.9 | I194: 72.8 | J194: 6.9 | K194: 6.37 | L194: 24.5 | M194: 136.6 | N194: 43.7 | O194: 161.8 | P194: Drip | Q194: 180 | R194: 3.09 | S194: 0.93 | T194: 3.1 | U194: 24.06 | V194: 26456 | W194: 533300 | X194: 636531 | Y194: 103231 | Z194: 9887 | AA194: 2.433 | AB194: 43.4
A195: SF10194 | B195: Tamil Nadu | C195: Nashik | D195: Rice | E195: Kharif | F195: 9.19 | G195: 756.7 | H195: 30.1 | I195: 82.9 | J195: 6.8 | K195: 7.24 | L195: 29.1 | M195: 172.5 | N195: 71.9 | O195: 155.2 | P195: Flood | Q195: 140.2 | R195: 4.73 | S195: 0.92 | T195: 3.24 | U195: 29.78 | V195: 24484 | W195: 589790 | X195: 729134 | Y195: 139344 | Z195: 21159 | AA195: 1.407 | AB195: 72.7
A196: SF10195 | B196: Maharashtra | C196: Raichur | D196: Pulses | E196: Rabi | F196: 12.32 | G196: 371 | H196: 24.4 | I196: 50.4 | J196: 8.3 | K196: 7.25 | L196: 25.7 | M196: 80 | N196: 28.9 | O196: 96.8 | P196: Rainfed | Q196: 224.9 | R196: 2.66 | S196: 0.94 | T196: 0.67 | U196: 8.25 | V196: 79182 | W196: 799704 | X196: 653252 | Y196: -146452 | Z196: 2643 | AA196: 3.121 | AB196: 39.6
A197: SF10196 | B197: Andhra Pradesh | C197: Erode | D197: Cotton | E197: Kharif | F197: 1.06 | G197: 702 | H197: 22.4 | I197: 57.3 | J197: 6.7 | K197: 6.93 | L197: 34.9 | M197: 91.7 | N197: 63.1 | O197: 105.8 | P197: Flood | Q197: 227.4 | R197: 5.51 | S197: 0.75 | T197: 1.72 | U197: 1.82 | V197: 76512 | W197: 76346 | X197: 139252 | Y197: 62906 | Z197: 1005 | AA197: 1.811 | AB197: 42.2
A198: SF10197 | B198: Andhra Pradesh | C198: Raichur | D198: Rice | E198: Kharif | F198: 4.53 | G198: 1118.6 | H198: 25.9 | I198: 69.2 | J198: 7 | K198: 6.35 | M198: 150.2 | N198: 79.1 | O198: 95.8 | P198: Sprinkler | Q198: 202 | R198: 7.96 | S198: 0.97 | T198: 3.08 | U198: 13.95 | V198: 26403 | W198: 301726 | X198: 368322 | Y198: 66596 | Z198: 6984 | AA198: 1.997 | AB198: 42.7
A199: SF10198 | B199: Madhya Pradesh | C199: Erode | D199: Wheat | E199: Kharif | F199: 7.71 | G199: 636.3 | H199: 25.7 | I199: 76.2 | J199: 7.4 | K199: 5.79 | L199: 40.8 | M199: 90.9 | N199: 61.2 | O199: 144.1 | P199: Drip | Q199: 212.6 | R199: 2.51 | S199: 0.74 | T199: 1.44 | U199: 11.1 | V199: 27940 | W199: 498280 | X199: 310134 | Y199: -188146 | Z199: 3735 | AA199: 2.972 | AB199: 66.5
A200: SF10199 | B200: Madhya Pradesh | C200: Guntur | D200: Wheat | E200: Kharif | F200: 5.9 | G200: 516.3 | H200: 26.7 | I200: 70.4 | J200: 4.9 | K200: 7.41 | L200: 34.4 | M200: 110.5 | N200: 78.1 | O200: 148.2 | P200: Flood | Q200: 138.8 | R200: 6.57 | S200: 0.71 | T200: 2.02 | U200: 11.92 | V200: 22196 | W200: 430850 | X200: 264576 | Y200: -166274 | Z200: 3837 | AA200: 3.107 | AB200: 44.9
A201: SF10200 | B201: Telangana | C201: Indore | D201: Rice | E201: Kharif | F201: 9.01 | G201: 1096.9 | H201: 28.7 | I201: 67.7 | J201: 7.8 | K201: 6.99 | L201: 29.6 | M201: 87.6 | N201: 42 | O201: 109.5 | P201: Rainfed | Q201: 198.9 | R201: 2.56 | S201: 0.75 | T201: 3.1 | U201: 27.93 | V201: 18625 | W201: 573606 | X201: 520196 | Y201: -53410 | Z201: 5948 | AA201: 4.696 | AB201: 57.5
A202: SF10201 | B202: Punjab | C202: Ludhiana | D202: Wheat | E202: Rabi | F202: 5.61 | G202: 227.1 | H202: 22.6 | I202: 77 | J202: 8.4 | K202: 6.19 | L202: 30.3 | M202: 148.9 | N202: 56.1 | O202: 91.2 | P202: Rainfed | Q202: 213.6 | R202: 7.57 | S202: 0.98 | T202: 1.44 | U202: 8.08 | V202: 20443 | W202: 386380 | X202: 165179 | Y202: -221201 | Z202: 1481 | AA202: 5.456 | AB202: 19.7
A203: SF10202 | B203: Telangana | C203: Rajkot | D203: Chilli | E203: Kharif | F203: 4.29 | G203: 720 | H203: 27.5 | I203: 71.6 | J203: 6.9 | K203: 8.13 | L203: 26 | M203: 160.9 | N203: 62.8 | O203: 100.2 | P203: Sprinkler | Q203: 171.6 | R203: 6.88 | S203: 0.79 | T203: 0.3 | U203: 1.29 | V203: 94967 | W203: 274657 | X203: 122507 | Y203: -152150 | Z203: 2873 | AA203: 0.449 | AB203: 43.2
A204: SF10203 | B204: Telangana | C204: Nalgonda | D204: Rice | E204: Kharif | F204: 6.06 | G204: 1331.9 | H204: 29 | I204: 64.2 | J204: 7.1 | K204: 5.67 | L204: 33.9 | M204: 106.4 | N204: 55.6 | O204: 76.4 | P204: Flood | Q204: 205.5 | R204: 7.46 | S204: 0.77 | T204: 0.68 | U204: 4.12 | V204: 20981 | W204: 435383 | X204: 86442 | Y204: -348941 | Z204: 11662 | AA204: 0.353 | AB204: 57.5
A205: SF10204 | B205: Telangana | C205: Nalgonda | D205: Wheat | E205: Rabi | F205: 1.01 | G205: 598.1 | H205: 25.9 | I205: 78.9 | J205: 7.8 | K205: 6.21 | L205: 23.1 | M205: 150.6 | N205: 41 | O205: 80.4 | P205: Flood | Q205: 82 | R205: 6.12 | S205: 0.71 | T205: 2.23 | U205: 2.25 | V205: 22156 | W205: 60567 | X205: 49851 | Y205: -10716 | Z205: 694 | AA205: 3.242 | AB205: 49.5
...

Sheet Cleaning_Reference
A1: Data Cleaning Reference Table
A2: Per-crop yield quartiles, used to impute missing yield values and cap statistical outliers (IQR method).
A3: Source: computed from Raw_Data (Yield_Tonnes_Ha) using pandas .quantile() â€” Q1=25th pct, Q3=75th pct, IQR=Q3-Q1, Upper Bound=Q3+1.5*IQR
A5: Crop | B5: Median_Yield_t_ha | C5: Q1_25pct | D5: Q3_75pct | E5: IQR | F5: Upper_Bound_Cap
A6: Chilli | B6: 1.56 | C6: 0.88 | D6: 2.12 | E6: 1.24 | F6: 3.98
A7: Cotton | B7: 1.24 | C7: 0.85 | D7: 1.6 | E7: 0.75 | F7: 2.73
A8: Groundnut | B8: 1.4 | C8: 0.86 | D8: 1.74 | E8: 0.88 | F8: 3.06
A9: Maize | B9: 2.85 | C9: 1.83 | D9: 3.65 | E9: 1.82 | F9: 6.38
A10: Pulses | B10: 0.94 | C10: 0.57 | D10: 1.24 | E10: 0.67 | F10: 2.24
A11: Rice | B11: 2.46 | C11: 1.59 | D11: 3.33 | E11: 1.74 | F11: 5.94
A12: Sugarcane | B12: 48.03 | C12: 32.51 | D12: 61.92 | E12: 29.42 | F12: 106.05
A13: Wheat | B13: 2.22 | C13: 1.45 | D13: 2.77 | E13: 1.32 | F13: 4.75

Sheet Cleaned_Data
A1: Farm ID | B1: State | C1: District | D1: Crop | E1: Season | F1: Farm Area Hectares | G1: Rainfall mm | H1: Avg Temperature C | I1: Humidity pct | J1: Sunlight Hours Day | K1: Soil pH | L1: Soil Moisture pct | M1: Nitrogen kg ha | N1: Phosphorus kg ha | O1: Potassium kg ha | P1: Irrigation Method | Q1: Fertilizer kg ha | R1: Pesticide Litre ha | S1: Seed Quality Score | T1: Yield Tonnes Ha | U1: Production Tonnes | V1: Market Price INR Tonne | W1: Total Cost INR | X1: Revenue INR | Y1: Profit INR | Z1: Water Used m3 | AA1: Water Efficiency t per 1000m3 | AB1: Disease Pest Risk pct | AC1: Rainfall Imputed | AD1: SoilMoisture Imputed | AE1: Yield Status | AF1: Production Recalculated t
A2: =Raw_Data!A2 -> SF10001 | B2: =Raw_Data!B2 -> Andhra Pradesh | C2: =Raw_Data!C2 -> Rajkot | D2: =Raw_Data!D2 -> Wheat | E2: =Raw_Data!E2 -> Kharif | F2: =Raw_Data!F2 -> 0.53 | G2: =IF(Raw_Data!G2="",ROUND(AVERAGEIFS(Raw_Data!$G$2:$G$4001,Raw_Data!$E$2:$E$4001,E2),1),Raw_Data!G2) -> 486.4 | H2: =Raw_Data!H2 -> 24.3 | I2: =Raw_Data!I2 -> 69.1 | J2: =Raw_Data!J2 -> 5.8 | K2: =Raw_Data!K2 -> 7.14 | L2: =IF(Raw_Data!L2="",ROUND(AVERAGEIFS(Raw_Data!$L$2:$L$4001,Raw_Data!$E$2:$E$4001,E2),1),Raw_Data!L2) -> 32.8 | M2: =Raw_Data!M2 -> 75.8 | N2: =Raw_Data!N2 -> 61.3 | O2: =Raw_Data!O2 -> 91 | P2: =Raw_Data!P2 -> Drip | Q2: =Raw_Data!Q2 -> 242.7 | R2: =Raw_Data!R2 -> 4.33 | S2: =Raw_Data!S2 -> 0.76 | T2: =IF(Raw_Data!T2="",ROUND(AVERAGEIFS(Raw_Data!$T$2:$T$4001,Raw_Data!$E$2:$E$4001,E2,Raw_Data!$D$2:$D$4001,D2),2),IF(Raw_Data!T2>INDEX(Cleaning_Reference!$F$6:$F$13,MATCH(D2,Cleaning_Reference!$A$6:$A$13,0)),INDEX(Cleaning_Reference!$F$6:$F$13,MATCH(D2,Cleaning_Reference!$A$6:$A$13,0)),Raw_Data!T2)) -> 2.46 | U2: =Raw_Data!U2 -> 1.3 | V2: =Raw_Data!V2 -> 23700 | W2: =Raw_Data!W2 -> 42662 | X2: =Raw_Data!X2 -> 30810 | Y2: =Raw_Data!Y2 -> -11852 | Z2: =Raw_Data!Z2 -> 237 | AA2: =Raw_Data!AA2 -> 5.485 | AB2: =Raw_Data!AB2 -> 55.3 | AC2: =IF(Raw_Data!G2="","Yes","No") -> No | AD2: =IF(Raw_Data!L2="","Yes","No") -> No | AE2: =IF(Raw_Data!T2="","Imputed",IF(Raw_Data!T2>INDEX(Cleaning_Reference!$F$6:$F$13,MATCH(D2,Cleaning_Reference!$A$6:$A$13,0)),"Capped","Original")) -> Original | AF2: =ROUND(T2*F2,2) -> 1.3
A3: =Raw_Data!A3 -> SF10002 | B3: =Raw_Data!B3 -> Maharashtra | C3: =Raw_Data!C3 -> Nalgonda | D3: =Raw_Data!D3 -> Maize | E3: =Raw_Data!E3 -> Kharif | F3: =Raw_Data!F3 -> 6.53 | G3: =IF(Raw_Data!G3="",ROUND(AVERAGEIFS(Raw_Data!$G$2:$G$4001,Raw_Data!$E$2:$E$4001,E3),1),Raw_Data!G3) -> 855.4 | H3: =Raw_Data!H3 -> 25.7 | I3: =Raw_Data!I3 -> 78.4 | J3: =Raw_Data!J3 -> 5.1 | K3: =Raw_Data!K3 -> 5.2 | L3: =IF(Raw_Data!L3="",ROUND(AVERAGEIFS(Raw_Data!$L$2:$L$4001,Raw_Data!$E$2:$E$4001,E3),1),Raw_Data!L3) -> 32 | M3: =Raw_Data!M3 -> 82.1 | N3: =Raw_Data!N3 -> 35.4 | O3: =Raw_Data!O3 -> 121.8 | P3: =Raw_Data!P3 -> Flood | Q3: =Raw_Data!Q3 -> 271.4 | R3: =Raw_Data!R3 -> 6.86 | S3: =Raw_Data!S3 -> 0.94 | T3: =IF(Raw_Data!T3="",ROUND(AVERAGEIFS(Raw_Data!$T$2:$T$4001,Raw_Data!$E$2:$E$4001,E3,Raw_Data!$D$2:$D$4001,D3),2),IF(Raw_Data!T3>INDEX(Cleaning_Reference!$F$6:$F$13,MATCH(D3,Cleaning_Reference!$A$6:$A$13,0)),INDEX(Cleaning_Reference!$F$6:$F$13,MATCH(D3,Cleaning_Reference!$A$6:$A$13,0)),Raw_Data!T3)) -> 0.3 | U3: =Raw_Data!U3 -> 1.96 | V3: =Raw_Data!V3 -> 20613 | W3: =Raw_Data!W3 -> 492351 | X3: =Raw_Data!X3 -> 40401 | Y3: =Raw_Data!Y3 -> -451950 | Z3: =Raw_Data!Z3 -> 4953 | AA3: =Raw_Data!AA3 -> 0.396 | AB3: =Raw_Data!AB3 -> 49.9 | AC3: =IF(Raw_Data!G3="","Yes","No") -> No | AD3: =IF(Raw_Data!L3="","Yes","No") -> No | AE3: =IF(Raw_Data!T3="","Imputed",IF(Raw_Data!T3>INDEX(Cleaning_Reference!$F$6:$F$13,MATCH(D3,Cleaning_Reference!$A$6:$A$13,0)),"Capped","Original")) -> Original | AF3: =ROUND(T3*F3,2) -> 1.96
A4: =Raw_Data!A4 -> SF10003 | B4: =Raw_Data!B4 -> Telangana | C4: =Raw_Data!C4 -> Warangal | D4: =Raw_Data!D4 -> Pulses | E4: =Raw_Data!E4 -> Rabi | F4: =Raw_Data!F4 -> 4.86 | G4: =IF(Raw_Data!G4="",ROUND(AVERAGEIFS(Raw_Data!$G$2:$G$4001,Raw_Data!$E$2:$E$4001,E4),1),Raw_Data!G4) -> 455.6 | H4: =Raw_Data!H4 -> 23.9 | I4: =Raw_Data!I4 -> 56.4 | J4: =Raw_Data!J4 -> 10.3 | K4: =Raw_Data!K4 -> 5.82 | L4: =IF(Raw_Data!L4="",ROUND(AVERAGEIFS(Raw_Data!$L$2:$L$4001,Raw_Data!$E$2:$E$4001,E4),1),Raw_Data!L4) -> 8.1 | M4: =Raw_Data!M4 -> 118.5 | N4: =Raw_Data!N4 -> 51.5 | O4: =Raw_Data!O4 -> 117.9 | P4: =Raw_Data!P4 -> Drip | Q4: =Raw_Data!Q4 -> 162.6 | R4: =Raw_Data!R4 -> 6.08 | S4: =Raw_Data!S4 -> 0.98 | T4: =IF(Raw_Data!T4="",ROUND(AVERAGEIFS(Raw_Data!$T$2:$T$4001,Raw_Data!$E$2:$E$4001,E4,Raw_Data!$D$2:$D$4001,D4),2),IF(Raw_Data!T4>INDEX(Cleaning_Reference!$F$6:$F$13,MATCH(D4,Cleaning_Reference!$A$6:$A$13,0)),INDEX(Cleaning_Reference!$F$6:$F$13,MATCH(D4,Cleaning_Reference!$A$6:$A$13,0)),Raw_Data!T4)) -> 0.52 | U4: =Raw_Data!U4 -> 2.53 | V4: =Raw_Data!V4 -> 75283 | W4: =Raw_Data!W4 -> 315210 | X4: =Raw_Data!X4 -> 190466 | Y4: =Raw_Data!Y4 -> -124744 | Z4: =Raw_Data!Z4 -> 1275 | AA4: =Raw_Data!AA4 -> 1.984 | AB4: =Raw_Data!AB4 -> 33.7 | AC4: =IF(Raw_Data!G4="","Yes","No") -> No | AD4: =IF(Raw_Data!L4="","Yes","No") -> No | AE4: =IF(Raw_Data!T4="","Imputed",IF(Raw_Data!T4>INDEX(Cleaning_Reference!$F$6:$F$13,MATCH(D4,Cleaning_Reference!$A$6:$A$13,0)),"Capped","Original")) -> Original | AF4: =ROUND(T4*F4,2) -> 2.53
A5: =Raw_Data!A5 -> SF10004 | B5: =Raw_Data!B5 -> Telangana | C5: =Raw_Data!C5 -> Indore | D5: =Raw_Data!D5 -> Rice | E5: =Raw_Data!E5 -> Kharif | F5: =Raw_Data!F5 -> 4.5 | G5: =IF(Raw_Data!G5="",ROUND(AVERAGEIFS(Raw_Data!$G$2:$G$4001,Raw_Data!$E$2:$E$4001,E5),1),Raw_Data!G5) -> 753.2 | H5: =Raw_Data!H5 -> 29.7 | I5: =Raw_Data!I5 -> 65.2 | J5: =Raw_Data!J5 -> 6.3 | K5: =Raw_Data!K5 -> 5.98 | L5: =IF(Raw_Data!L5="",ROUND(AVERAGEIFS(Raw_Data!$L$2:$L$4001,Raw_Data!$E$2:$E$4001,E5),1),Raw_Data!L5) -> 23.7 | M5: =Raw_Data!M5 -> 138.6 | N5: =Raw_Data!N5 -> 55.6 | O5: =Raw_Data!O5 -> 115.5 | P5: =Raw_Data!P5 -> Rainfed | Q5: =Raw_Data!Q5 -> 182.2 | R5: =Raw_Data!R5 -> 6.39 | S5: =Raw_Data!S5 -> 0.74 | T5: =IF(Raw_Data!T5="",ROUND(AVERAGEIFS(Raw_Data!$T$2:$T$4001,Raw_Data!$E$2:$E$4001,E5,Raw_Data!$D$2:$D$4001,D5),2),IF(Raw_Data!T5>INDEX(Cleaning_Reference!$F$6:$F$13,MATCH(D5,Cleaning_Reference!$A$6:$A$13,0)),INDEX(Cleaning_Reference!$F$6:$F$13,MATCH(D5,Cleaning_Reference!$A$6:$A$13,0)),Raw_Data!T5)) -> 1.84 | U5: =Raw_Data!U5 -> 8.28 | V5: =Raw_Data!V5 -> 24244 | W5: =Raw_Data!W5 -> 296444 | X5: =Raw_Data!X5 -> 200740 | Y5: =Raw_Data!Y5 -> -95704 | Z5: =Raw_Data!Z5 -> 3834 | AA5: =Raw_Data!AA5 -> 2.16 | AB5: =Raw_Data!AB5 -> 50.6 | AC5: =IF(Raw_Data!G5="","Yes","No") -> No | AD5: =IF(Raw_Data!L5="","Yes","No") -> No | AE5: =IF(Raw_Data!T5="","Imputed",IF(Raw_Data!T5>INDEX(Cleaning_Reference!$F$6:$F$13,MATCH(D5,Cleaning_Reference!$A$6:$A$13,0)),"Capped","Original")) -> Original | AF5: =ROUND(T5*F5,2) -> 8.28
A6: =Raw_Data!A6 -> SF10005 | B6: =Raw_Data!B6 -> Karnataka | C6: =Raw_Data!C6 -> Ludhiana | D6: =Raw_Data!D6 -> Maize | E6: =Raw_Data!E6 -> Zaid | F6: =Raw_Data!F6 -> 4.21 | G6: =IF(Raw_Data!G6="",ROUND(AVERAGEIFS(Raw_Data!$G$2:$G$4001,Raw_Data!$E$2:$E$4001,E6),1),Raw_Data!G6) -> 101.6 | H6: =Raw_Data!H6 -> 34.1 | I6: =Raw_Data!I6 -> 55.2 | J6: =Raw_Data!J6 -> 6.5 | K6: =Raw_Data!K6 -> 6.9 | L6: =IF(Raw_Data!L6="",ROUND(AVERAGEIFS(Raw_Data!$L$2:$L$4001,Raw_Data!$E$2:$E$4001,E6),1),Raw_Data!L6) -> 29.3 | M6: =Raw_Data!M6 -> 124.1 | N6: =Raw_Data!N6 -> 69 | O6: =Raw_Data!O6 -> 121.4 | P6: =Raw_Data!P6 -> Flood | Q6: =Raw_Data!Q6 -> 244.9 | R6: =Raw_Data!R6 -> 7.61 | S6: =Raw_Data!S6 -> 0.9 | T6: =IF(Raw_Data!T6="",ROUND(AVERAGEIFS(Raw_Data!$T$2:$T$4001,Raw_Data!$E$2:$E$4001,E6,Raw_Data!$D$2:$D$4001,D6),2),IF(Raw_Data!T6>INDEX(Cleaning_Reference!$F$6:$F$13,MATCH(D6,Cleaning_Reference!$A$6:$A$13,0)),INDEX(Cleaning_Reference!$F$6:$F$13,MATCH(D6,Cleaning_Reference!$A$6:$A$13,0)),Raw_Data!T6)) -> 2.21 | U6: =Raw_Data!U6 -> 9.3 | V6: =Raw_Data!V6 -> 20818 | W6: =Raw_Data!W6 -> 337959 | X6: =Raw_Data!X6 -> 193607 | Y6: =Raw_Data!Y6 -> -144352 | Z6: =Raw_Data!Z6 -> 3287 | AA6: =Raw_Data!AA6 -> 2.829 | AB6: =Raw_Data!AB6 -> 32.3 | AC6: =IF(Raw_Data!G6="","Yes","No") -> No | AD6: =IF(Raw_Data!L6="","Yes","No") -> No | AE6: =IF(Raw_Data!T6="","Imputed",IF(Raw_Data!T6>INDEX(Cleaning_Reference!$F$6:$F$13,MATCH(D6,Cleaning_Reference!$A$6:$A$13,0)),"Capped","Original")) -> Original | AF6: =ROUND(T6*F6,2) -> 9.3
A7: =Raw_Data!A7 -> SF10006 | B7: =Raw_Data!B7 -> Gujarat | C7: =Raw_Data!C7 -> Raichur | D7: =Raw_Data!D7 -> Pulses | E7: =Raw_Data!E7 -> Zaid | F7: =Raw_Data!F7 -> 5.46 | G7: =IF(Raw_Data!G7="",ROUND(AVERAGEIFS(Raw_Data!$G$2:$G$4001,Raw_Data!$E$2:$E$4001,E7),1),Raw_Data!G7) -> 356 | H7: =Raw_Data!H7 -> 33.6 | I7: =Raw_Data!I7 -> 49 | J7: =Raw_Data!J7 -> 8.3 | K7: =Raw_Data!K7 -> 6.93 | L7: =IF(Raw_Data!L7="",ROUND(AVERAGEIFS(Raw_Data!$L$2:$L$4001,Raw_Data!$E$2:$E$4001,E7),1),Raw_Data!L7) -> 11.4 | M7: =Raw_Data!M7 -> 105.1 | N7: =Raw_Data!N7 -> 34.7 | O7: =Raw_Data!O7 -> 78.7 | P7: =Raw_Data!P7 -> Rainfed | Q7: =Raw_Data!Q7 -> 58.8 | R7: =Raw_Data!R7 -> 4.48 | S7: =Raw_Data!S7 -> 0.89 | T7: =IF(Raw_Data!T7="",ROUND(AVERAGEIFS(Raw_Data!$T$2:$T$4001,Raw_Data!$E$2:$E$4001,E7,Raw_Data!$D$2:$D$4001,D7),2),IF(Raw_Data!T7>INDEX(Cleaning_Reference!$F$6:$F$13,MATCH(D7,Cleaning_Reference!$A$6:$A$13,0)),INDEX(Cleaning_Reference!$F$6:$F$13,MATCH(D7,Cleaning_Reference!$A$6:$A$13,0)),Raw_Data!T7)) -> 0.72 | U7: =Raw_Data!U7 -> 3.93 | V7: =Raw_Data!V7 -> 68593 | W7: =Raw_Data!W7 -> 302333 | X7: =Raw_Data!X7 -> 269570 | Y7: =Raw_Data!Y7 -> -32763 | Z7: =Raw_Data!Z7 -> 1093 | AA7: =Raw_Data!AA7 -> 3.596 | AB7: =Raw_Data!AB7 -> 57.1 | AC7: =IF(Raw_Data!G7="","Yes","No") -> No | AD7: =IF(Raw_Data!L7="","Yes","No") -> No | AE7: =IF(Raw_Data!T7="","Imputed",IF(Raw_Data!T7>INDEX(Cleaning_Reference!$F$6:$F$13,MATCH(D7,Cleaning_Reference!$A$6:$A$13,0)),"Capped","Original")) -> Original | AF7: =ROUND(T7*F7,2) -> 3.93
A8: =Raw_Data!A8 -> SF10007 | B8: =Raw_Data!B8 -> Telangana | C8: =Raw_Data!C8 -> Warangal | D8: =Raw_Data!D8 -> Wheat | E8: =Raw_Data!E8 -> Rabi | F8: =Raw_Data!F8 -> 8.13 | G8: =IF(Raw_Data!G8="",ROUND(AVERAGEIFS(Raw_Data!$G$2:$G$4001,Raw_Data!$E$2:$E$4001,E8),1),Raw_Data!G8) -> 432.2 | H8: =Raw_Data!H8 -> 23.5 | I8: =Raw_Data!I8 -> 50.8 | J8: =Raw_Data!J8 -> 9.5 | K8: =Raw_Data!K8 -> 6.96 | L8: =IF(Raw_Data!L8="",ROUND(AVERAGEIFS(Raw_Data!$L$2:$L$4001,Raw_Data!$E$2:$E$4001,E8),1),Raw_Data!L8) -> 24.7 | M8: =Raw_Data!M8 -> 115.8 | N8: =Raw_Data!N8 -> 69.4 | O8: =Raw_Data!O8 -> 109.8 | P8: =Raw_Data!P8 -> Rainfed | Q8: =Raw_Data!Q8 -> 181.6 | R8: =Raw_Data!R8 -> 7.99 | S8: =Raw_Data!S8 -> 0.87 | T8: =IF(Raw_Data!T8="",ROUND(AVERAGEIFS(Raw_Data!$T$2:$T$4001,Raw_Data!$E$2:$E$4001,E8,Raw_Data!$D$2:$D$4001,D8),2),IF(Raw_Data!T8>INDEX(Cleaning_Reference!$F$6:$F$13,MATCH(D8,Cleaning_Reference!$A$6:$A$13,0)),INDEX(Cleaning_Reference!$F$6:$F$13,MATCH(D8,Cleaning_Reference!$A$6:$A$13,0)),Raw_Data!T8)) -> 2.53 | U8: =Raw_Data!U8 -> 20.57 | V8: =Raw_Data!V8 -> 22951 | W8: =Raw_Data!W8 -> 513341 | X8: =Raw_Data!X8 -> 472102 | Y8: =Raw_Data!Y8 -> -41239 | Z8: =Raw_Data!Z8 -> 2368 | AA8: =Raw_Data!AA8 -> 8.687 | AB8: =Raw_Data!AB8 -> 31.6 | AC8: =IF(Raw_Data!G8="","Yes","No") -> No | AD8: =IF(Raw_Data!L8="","Yes","No") -> No | AE8: =IF(Raw_Data!T8="","Imputed",IF(Raw_Data!T8>INDEX(Cleaning_Reference!$F$6:$F$13,MATCH(D8,Cleaning_Reference!$A$6:$A$13,0)),"Capped","Original")) -> Original | AF8: =ROUND(T8*F8,2) -> 20.57
A9: =Raw_Data!A9 -> SF10008 | B9: =Raw_Data!B9 -> Tamil Nadu | C9: =Raw_Data!C9 -> Ludhiana | D9: =Raw_Data!D9 -> Pulses | E9: =Raw_Data!E9 -> Kharif | F9: =Raw_Data!F9 -> 5.34 | G9: =IF(Raw_Data!G9="",ROUND(AVERAGEIFS(Raw_Data!$G$2:$G$4001,Raw_Data!$E$2:$E$4001,E9),1),Raw_Data!G9) -> 860.2 | H9: =Raw_Data!H9 -> 29 | I9: =Raw_Data!I9 -> 64.9 | J9: =Raw_Data!J9 -> 7.9 | K9: =Raw_Data!K9 -> 6.09 | L9: =IF(Raw_Data!L9="",ROUND(AVERAGEIFS(Raw_Data!$L$2:$L$4001,Raw_Data!$E$2:$E$4001,E9),1),Raw_Data!L9) -> 36.9 | M9: =Raw_Data!M9 -> 112.7 | N9: =Raw_Data!N9 -> 60.9 | O9: =Raw_Data!O9 -> 115.9 | P9: =Raw_Data!P9 -> Sprinkler | Q9: =Raw_Data!Q9 -> 245.8 | R9: =Raw_Data!R9 -> 5.89 | S9: =Raw_Data!S9 -> 0.7 | T9: =IF(Raw_Data!T9="",ROUND(AVERAGEIFS(Raw_Data!$T$2:$T$4001,Raw_Data!$E$2:$E$4001,E9,Raw_Data!$D$2:$D$4001,D9),2),IF(Raw_Data!T9>INDEX(Cleaning_Reference!$F$6:$F$13,MATCH(D9,Cleaning_Reference!$A$6:$A$13,0)),INDEX(Cleaning_Reference!$F$6:$F$13,MATCH(D9,Cleaning_Reference!$A$6:$A$13,0)),Raw_Data!T9)) -> 1.18 | U9: =Raw_Data!U9 -> 6.3 | V9: =Raw_Data!V9 -> 70042 | W9: =Raw_Data!W9 -> 436200 | X9: =Raw_Data!X9 -> 441265 | Y9: =Raw_Data!Y9 -> 5065 | Z9: =Raw_Data!Z9 -> 1704 | AA9: =Raw_Data!AA9 -> 3.697 | AB9: =Raw_Data!AB9 -> 54.2 | AC9: =IF(Raw_Data!G9="","Yes","No") -> No | AD9: =IF(Raw_Data!L9="","Yes","No") -> No | AE9: =IF(Raw_Data!T9="","Imputed",IF(Raw_Data!T9>INDEX(Cleaning_Reference!$F$6:$F$13,MATCH(D9,Cleaning_Reference!$A$6:$A$13,0)),"Capped","Original")) -> Original | AF9: =ROUND(T9*F9,2) -> 6.3
A10: =Raw_Data!A10 -> SF10009 | B10: =Raw_Data!B10 -> Karnataka | C10: =Raw_Data!C10 -> Guntur | D10: =Raw_Data!D10 -> Cotton | E10: =Raw_Data!E10 -> Zaid | F10: =Raw_Data!F10 -> 6.98 | G10: =IF(Raw_Data!G10="",ROUND(AVERAGEIFS(Raw_Data!$G$2:$G$4001,Raw_Data!$E$2:$E$4001,E10),1),Raw_Data!G10) -> 624.7 | H10: =Raw_Data!H10 -> 33.4 | I10: =Raw_Data!I10 -> 46.8 | J10: =Raw_Data!J10 -> 7.9 | K10: =Raw_Data!K10 -> 6.41 | L10: =IF(Raw_Data!L10="",ROUND(AVERAGEIFS(Raw_Data!$L$2:$L$4001,Raw_Data!$E$2:$E$4001,E10),1),Raw_Data!L10) -> 12.3 | M10: =Raw_Data!M10 -> 66.9 | N10: =Raw_Data!N10 -> 47.6 | O10: =Raw_Data!O10 -> 134.2 | P10: =Raw_Data!P10 -> Sprinkler | Q10: =Raw_Data!Q10 -> 190.7 | R10: =Raw_Data!R10 -> 2.21 | S10: =Raw_Data!S10 -> 0.88 | T10: =IF(Raw_Data!T10="",ROUND(AVERAGEIFS(Raw_Data!$T$2:$T$4001,Raw_Data!$E$2:$E$4001,E10,Raw_Data!$D$2:$D$4001,D10),2),IF(Raw_Data!T10>INDEX(Cleaning_Reference!$F$6:$F$13,MATCH(D10,Cleaning_Reference!$A$6:$A$13,0)),INDEX(Cleaning_Reference!$F$6:$F$13,MATCH(D10,Cleaning_Reference!$A$6:$A$13,0)),Raw_Data!T10)) -> 1.53 | U10: =Raw_Data!U10 -> 10.68 | V10: =Raw_Data!V10 -> 70771 | W10: =Raw_Data!W10 -> 525129 | X10: =Raw_Data!X10 -> 755834 | Y10: =Raw_Data!Y10 -> 230705 | Z10: =Raw_Data!Z10 -> 5079 | AA10: =Raw_Data!AA10 -> 2.103 | AB10: =Raw_Data!AB10 -> 54.7 | AC10: =IF(Raw_Data!G10="","Yes","No") -> No | AD10: =IF(Raw_Data!L10="","Yes","No") -> No | AE10: =IF(Raw_Data!T10="","Imputed",IF(Raw_Data!T10>INDEX(Cleaning_Reference!$F$6:$F$13,MATCH(D10,Cleaning_Reference!$A$6:$A$13,0)),"Capped","Original")) -> Original | AF10: =ROUND(T10*F10,2) -> 10.68
A11: =Raw_Data!A11 -> SF10010 | B11: =Raw_Data!B11 -> Tamil Nadu | C11: =Raw_Data!C11 -> Raichur | D11: =Raw_Data!D11 -> Chilli | E11: =Raw_Data!E11 -> Rabi | F11: =Raw_Data!F11 -> 13.69 | G11: =IF(Raw_Data!G11="",ROUND(AVERAGEIFS(Raw_Data!$G$2:$G$4001,Raw_Data!$E$2:$E$4001,E11),1),Raw_Data!G11) -> 415.8 | H11: =Raw_Data!H11 -> 22.3 | I11: =Raw_Data!I11 -> 57.3 | J11: =Raw_Data!J11 -> 8.6 | K11: =Raw_Data!K11 -> 6.6 | L11: =IF(Raw_Data!L11="",ROUND(AVERAGEIFS(Raw_Data!$L$2:$L$4001,Raw_Data!$E$2:$E$4001,E11),1),Raw_Data!L11) -> 23.3 | M11: =Raw_Data!M11 -> 117.9 | N11: =Raw_Data!N11 -> 37.2 | O11: =Raw_Data!O11 -> 116.6 | P11: =Raw_Data!P11 -> Drip | Q11: =Raw_Data!Q11 -> 168.8 | R11: =Raw_Data!R11 -> 7.29 | S11: =Raw_Data!S11 -> 0.7 | T11: =IF(Raw_Data!T11="",ROUND(AVERAGEIFS(Raw_Data!$T$2:$T$4001,Raw_Data!$E$2:$E$4001,E11,Raw_Data!$D$2:$D$4001,D11),2),IF(Raw_Data!T11>INDEX(Cleaning_Reference!$F$6:$F$13,MATCH(D11,Cleaning_Reference!$A$6:$A$13,0)),INDEX(Cleaning_Reference!$F$6:$F$13,MATCH(D11,Cleaning_Reference!$A$6:$A$13,0)),Raw_Data!T11)) -> 2.29 | U11: =Raw_Data!U11 -> 31.35 | V11: =Raw_Data!V11 -> 94383 | W11: =Raw_Data!W11 -> 1004072 | X11: =Raw_Data!X11 -> 2958907 | Y11: =Raw_Data!Y11 -> 1954835 | Z11: =Raw_Data!Z11 -> 5984 | AA11: =Raw_Data!AA11 -> 5.239 | AB11: =Raw_Data!AB11 -> 41.7 | AC11: =IF(Raw_Data!G11="","Yes","No") -> No | AD11: =IF(Raw_Data!L11="","Yes","No") -> No | AE11: =IF(Raw_Data!T11="","Imputed",IF(Raw_Data!T11>INDEX(Cleaning_Reference!$F$6:$F$13,MATCH(D11,Cleaning_Reference!$A$6:$A$13,0)),"Capped","Original")) -> Original | AF11: =ROUND(T11*F11,2) -> 31.35
A12: =Raw_Data!A12 -> SF10011 | B12: =Raw_Data!B12 -> Maharashtra | C12: =Raw_Data!C12 -> Krishna | D12: =Raw_Data!D12 -> Wheat | E12: =Raw_Data!E12 -> Rabi | F12: =Raw_Data!F12 -> 4.7 | G12: =IF(Raw_Data!G12="",ROUND(AVERAGEIFS(Raw_Data!$G$2:$G$4001,Raw_Data!$E$2:$E$4001,E12),1),Raw_Data!G12) -> 390.8 | H12: =Raw_Data!H12 -> 24.5 | I12: =Raw_Data!I12 -> 43.5 | J12: =Raw_Data!J12 -> 7.8 | K12: =Raw_Data!K12 -> 5.93 | L12: =IF(Raw_Data!L12="",ROUND(AVERAGEIFS(Raw_Data!$L$2:$L$4001,Raw_Data!$E$2:$E$4001,E12),1),Raw_Data!L12) -> 25.2 | M12: =Raw_Data!M12 -> 137.9 | N12: =Raw_Data!N12 -> 31.4 | O12: =Raw_Data!O12 -> 70 | P12: =Raw_Data!P12 -> Sprinkler | Q12: =Raw_Data!Q12 -> 224.4 | R12: =Raw_Data!R12 -> 5.9 | S12: =Raw_Data!S12 -> 0.89 | T12: =IF(Raw_Data!T12="",ROUND(AVERAGEIFS(Raw_Data!$T$2:$T$4001,Raw_Data!$E$2:$E$4001,E12,Raw_Data!$D$2:$D$4001,D12),2),IF(Raw_Data!T12>INDEX(Cleaning_Reference!$F$6:$F$13,MATCH(D12,Cleaning_Reference!$A$6:$A$13,0)),INDEX(Cleaning_Reference!$F$6:$F$13,MATCH(D12,Cleaning_Reference!$A$6:$A$13,0)),Raw_Data!T12)) -> 1.44 | U12: =Raw_Data!U12 -> 6.77 | V12: =Raw_Data!V12 -> 20806 | W12: =Raw_Data!W12 -> 289759 | X12: =Raw_Data!X12 -> 140857 | Y12: =Raw_Data!Y12 -> -148902 | Z12: =Raw_Data!Z12 -> 2371 | AA12: =Raw_Data!AA12 -> 2.855 | AB12: =Raw_Data!AB12 -> 33.5 | AC12: =IF(Raw_Data!G12="","Yes","No") -> No | AD12: =IF(Raw_Data!L12="","Yes","No") -> No | AE12: =IF(Raw_Data!T12="","Imputed",IF(Raw_Data!T12>INDEX(Cleaning_Reference!$F$6:$F$13,MATCH(D12,Cleaning_Reference!$A$6:$A$13,0)),"Capped","Original")) -> Original | AF12: =ROUND(T12*F12,2) -> 6.77
A13: =Raw_Data!A13 -> SF10012 | B13: =Raw_Data!B13 -> Telangana | C13: =Raw_Data!C13 -> Rajkot | D13: =Raw_Data!D13 -> Maize | E13: =Raw_Data!E13 -> Rabi | F13: =Raw_Data!F13 -> 14.07 | G13: =IF(Raw_Data!G13="",ROUND(AVERAGEIFS(Raw_Data!$G$2:$G$4001,Raw_Data!$E$2:$E$4001,E13),1),Raw_Data!G13) -> 315.3 | H13: =Raw_Data!H13 -> 24.2 | I13: =Raw_Data!I13 -> 53.7 | J13: =Raw_Data!J13 -> 5.9 | K13: =Raw_Data!K13 -> 5.87 | L13: =IF(Raw_Data!L13="",ROUND(AVERAGEIFS(Raw_Data!$L$2:$L$4001,Raw_Data!$E$2:$E$4001,E13),1),Raw_Data!L13) -> 29.4 | M13: =Raw_Data!M13 -> 100.6 | N13: =Raw_Data!N13 -> 50.8 | O13: =Raw_Data!O13 -> 65.8 | P13: =Raw_Data!P13 -> Drip | Q13: =Raw_Data!Q13 -> 178.7 | R13: =Raw_Data!R13 -> 5.34 | S13: =Raw_Data!S13 -> 0.71 | T13: =IF(Raw_Data!T13="",ROUND(AVERAGEIFS(Raw_Data!$T$2:$T$4001,Raw_Data!$E$2:$E$4001,E13,Raw_Data!$D$2:$D$4001,D13),2),IF(Raw_Data!T13>INDEX(Cleaning_Reference!$F$6:$F$13,MATCH(D13,Cleaning_Reference!$A$6:$A$13,0)),INDEX(Cleaning_Reference!$F$6:$F$13,MATCH(D13,Cleaning_Reference!$A$6:$A$13,0)),Raw_Data!T13)) -> 1.36 | U13: =Raw_Data!U13 -> 19.14 | V13: =Raw_Data!V13 -> 20120 | W13: =Raw_Data!W13 -> 964512 | X13: =Raw_Data!X13 -> 385097 | Y13: =Raw_Data!Y13 -> -579415 | Z13: =Raw_Data!Z13 -> 7467 | AA13: =Raw_Data!AA13 -> 2.563 | AB13: =Raw_Data!AB13 -> 35 | AC13: =IF(Raw_Data!G13="","Yes","No") -> No | AD13: =IF(Raw_Data!L13="","Yes","No") -> No | AE13: =IF(Raw_Data!T13="","Imputed",IF(Raw_Data!T13>INDEX(Cleaning_Reference!$F$6:$F$13,MATCH(D13,Cleaning_Reference!$A$6:$A$13,0)),"Capped","Original")) -> Original | AF13: =ROUND(T13*F13,2) -> 19.14
... A4001: =Raw_Data!A4001 -> SF14000 | B4001: =Raw_Data!B4001 -> Punjab | C4001: =Raw_Data!C4001 -> Nashik | D4001: =Raw_Data!D4001 -> Wheat | E4001: =Raw_Data!E4001 -> Kharif | F4001: =Raw_Data!F4001 -> 3.31 | G4001: =IF(Raw_Data!G4001="",ROUND(AVERAGEIFS(Raw_Data!$G$2:$G$4001,Raw_Data!$E$2:$E$4001,E4001),1),Raw_Data!G4001) -> 984.3 | H4001: =Raw_Data!H4001 -> 25.8 | I4001: =Raw_Data!I4001 -> 77.2 | J4001: =Raw_Data!J4001 -> 5.9 | K4001: =Raw_Data!K4001 -> 6.16 | L4001: =IF(Raw_Data!L4001="",ROUND(AVERAGEIFS(Raw_Data!$L$2:$L$4001,Raw_Data!$E$2:$E$4001,E4001),1),Raw_Data!L4001) -> 35.7 | M4001: =Raw_Data!M4001 -> 137.1 | N4001: =Raw_Data!N4001 -> 92.6 | O4001: =Raw_Data!O4001 -> 145.5 | P4001: =Raw_Data!P4001 -> Sprinkler | Q4001: =Raw_Data!Q4001 -> 205.9 | R4001: =Raw_Data!R4001 -> 6.72 | S4001: =Raw_Data!S4001 -> 0.99 | T4001: =IF(Raw_Data!T4001="",ROUND(AVERAGEIFS(Raw_Data!$T$2:$T$4001,Raw_Data!$E$2:$E$4001,E4001,Raw_Data!$D$2:$D$4001,D4001),2),IF(Raw_Data!T4001>INDEX(Cleaning_Reference!$F$6:$F$13,MATCH(D4001,Cleaning_Reference!$A$6:$A$13,0)),INDEX(Cleaning_Reference!$F$6:$F$13,MATCH(D4001,Cleaning_Reference!$A$6:$A$13,0)),Raw_Data!T4001)) -> 2.36 | U4001: =Raw_Data!U4001 -> 7.81 | V4001: =Raw_Data!V4001 -> 28812 | W4001: =Raw_Data!W4001 -> 263872 | X4001: =Raw_Data!X4001 -> 225022 | Y4001: =Raw_Data!Y4001 -> -38850 | Z4001: =Raw_Data!Z4001 -> 1800 | AA4001: =Raw_Data!AA4001 -> 4.339 | AB4001: =Raw_Data!AB4001 -> 62.3 | AC4001: =IF(Raw_Data!G4001="","Yes","No") -> No | AD4001: =IF(Raw_Data!L4001="","Yes","No") -> No | AE4001: =IF(Raw_Data!T4001="","Imputed",IF(Raw_Data!T4001>INDEX(Cleaning_Reference!$F$6:$F$13,MATCH(D4001,Cleaning_Reference!$A$6:$A$13,0)),"Capped","Original")) -> Original | AF4001: =ROUND(T4001*F4001,2) -> 7.81

Sheet Season_Summary
A1: Seasonal Performance Summary
A2: Key metrics averaged/summed across all farms, by season (source: Cleaned_Data)
A4: Metric | B4: Kharif | C4: Rabi | D4: Zaid
A5: Number of Farms | B5: =COUNTIF(Cleaned_Data!$E$2:$E$4001,"Kharif") -> 1779 | C5: =COUNTIF(Cleaned_Data!$E$2:$E$4001,"Rabi") -> 1627 | D5: =COUNTIF(Cleaned_Data!$E$2:$E$4001,"Zaid") -> 594
A6: Avg Farm Area (ha) | B6: =AVERAGEIFS(Cleaned_Data!$F$2:$F$4001,Cleaned_Data!$E$2:$E$4001,"Kharif") -> 7.9449241 | C6: =AVERAGEIFS(Cleaned_Data!$F$2:$F$4001,Cleaned_Data!$E$2:$E$4001,"Rabi") -> 7.7522065 | D6: =AVERAGEIFS(Cleaned_Data!$F$2:$F$4001,Cleaned_Data!$E$2:$E$4001,"Zaid") -> 8.0912458
A7: Avg Rainfall (mm) | B7: =AVERAGEIFS(Cleaned_Data!$G$2:$G$4001,Cleaned_Data!$E$2:$E$4001,"Kharif") -> 852.08437 | C7: =AVERAGEIFS(Cleaned_Data!$G$2:$G$4001,Cleaned_Data!$E$2:$E$4001,"Rabi") -> 436.00012 | D7: =AVERAGEIFS(Cleaned_Data!$G$2:$G$4001,Cleaned_Data!$E$2:$E$4001,"Zaid") -> 299.42138
A8: Avg Temperature (C) | B8: =AVERAGEIFS(Cleaned_Data!$H$2:$H$4001,Cleaned_Data!$E$2:$E$4001,"Kharif") -> 28.454019 | C8: =AVERAGEIFS(Cleaned_Data!$H$2:$H$4001,Cleaned_Data!$E$2:$E$4001,"Rabi") -> 23.489183 | D8: =AVERAGEIFS(Cleaned_Data!$H$2:$H$4001,Cleaned_Data!$E$2:$E$4001,"Zaid") -> 31.042088
A9: Avg Humidity (%) | B9: =AVERAGEIFS(Cleaned_Data!$I$2:$I$4001,Cleaned_Data!$E$2:$E$4001,"Kharif") -> 71.812591 | C9: =AVERAGEIFS(Cleaned_Data!$I$2:$I$4001,Cleaned_Data!$E$2:$E$4001,"Rabi") -> 57.893178 | D9: =AVERAGEIFS(Cleaned_Data!$I$2:$I$4001,Cleaned_Data!$E$2:$E$4001,"Zaid") -> 52.012121
A10: Avg Sunlight (hrs/day) | B10: =AVERAGEIFS(Cleaned_Data!$J$2:$J$4001,Cleaned_Data!$E$2:$E$4001,"Kharif") -> 6.7933671 | C10: =AVERAGEIFS(Cleaned_Data!$J$2:$J$4001,Cleaned_Data!$E$2:$E$4001,"Rabi") -> 7.5897972 | D10: =AVERAGEIFS(Cleaned_Data!$J$2:$J$4001,Cleaned_Data!$E$2:$E$4001,"Zaid") -> 8.1787879
A11: Avg Soil pH | B11: =AVERAGEIFS(Cleaned_Data!$K$2:$K$4001,Cleaned_Data!$E$2:$E$4001,"Kharif") -> 6.7279933 | C11: =AVERAGEIFS(Cleaned_Data!$K$2:$K$4001,Cleaned_Data!$E$2:$E$4001,"Rabi") -> 6.6737492 | D11: =AVERAGEIFS(Cleaned_Data!$K$2:$K$4001,Cleaned_Data!$E$2:$E$4001,"Zaid") -> 6.6948653
A12: Avg Soil Moisture (%) | B12: =AVERAGEIFS(Cleaned_Data!$L$2:$L$4001,Cleaned_Data!$E$2:$E$4001,"Kharif") -> 31.198426 | C12: =AVERAGEIFS(Cleaned_Data!$L$2:$L$4001,Cleaned_Data!$E$2:$E$4001,"Rabi") -> 24.051014 | D12: =AVERAGEIFS(Cleaned_Data!$L$2:$L$4001,Cleaned_Data!$E$2:$E$4001,"Zaid") -> 19.170539
A13: Avg Fertilizer (kg/ha) | B13: =AVERAGEIFS(Cleaned_Data!$Q$2:$Q$4001,Cleaned_Data!$E$2:$E$4001,"Kharif") -> 187.07797 | C13: =AVERAGEIFS(Cleaned_Data!$Q$2:$Q$4001,Cleaned_Data!$E$2:$E$4001,"Rabi") -> 185.40707 | D13: =AVERAGEIFS(Cleaned_Data!$Q$2:$Q$4001,Cleaned_Data!$E$2:$E$4001,"Zaid") -> 184.63805
A14: Avg Pesticide (L/ha) | B14: =AVERAGEIFS(Cleaned_Data!$R$2:$R$4001,Cleaned_Data!$E$2:$E$4001,"Kharif") -> 5.079747 | C14: =AVERAGEIFS(Cleaned_Data!$R$2:$R$4001,Cleaned_Data!$E$2:$E$4001,"Rabi") -> 5.0246896 | D14: =AVERAGEIFS(Cleaned_Data!$R$2:$R$4001,Cleaned_Data!$E$2:$E$4001,"Zaid") -> 5.1712121
A15: Avg Seed Quality Score | B15: =AVERAGEIFS(Cleaned_Data!$S$2:$S$4001,Cleaned_Data!$E$2:$E$4001,"Kharif") -> 0.82161327 | C15: =AVERAGEIFS(Cleaned_Data!$S$2:$S$4001,Cleaned_Data!$E$2:$E$4001,"Rabi") -> 0.83216964 | D15: =AVERAGEIFS(Cleaned_Data!$S$2:$S$4001,Cleaned_Data!$E$2:$E$4001,"Zaid") -> 0.82316498
A16: Avg Yield (t/ha) | B16: =AVERAGEIFS(Cleaned_Data!$T$2:$T$4001,Cleaned_Data!$E$2:$E$4001,"Kharif") -> 5.6300843 | C16: =AVERAGEIFS(Cleaned_Data!$T$2:$T$4001,Cleaned_Data!$E$2:$E$4001,"Rabi") -> 5.0920897 | D16: =AVERAGEIFS(Cleaned_Data!$T$2:$T$4001,Cleaned_Data!$E$2:$E$4001,"Zaid") -> 4.6372054
A17: Total Production (t) | B17: =SUMIFS(Cleaned_Data!$U$2:$U$4001,Cleaned_Data!$E$2:$E$4001,"Kharif") -> 82387.61 | C17: =SUMIFS(Cleaned_Data!$U$2:$U$4001,Cleaned_Data!$E$2:$E$4001,"Rabi") -> 67498.88 | D17: =SUMIFS(Cleaned_Data!$U$2:$U$4001,Cleaned_Data!$E$2:$E$4001,"Zaid") -> 23098.35
A18: Avg Market Price (INR/t) | B18: =AVERAGEIFS(Cleaned_Data!$V$2:$V$4001,Cleaned_Data!$E$2:$E$4001,"Kharif") -> 44850.906 | C18: =AVERAGEIFS(Cleaned_Data!$V$2:$V$4001,Cleaned_Data!$E$2:$E$4001,"Rabi") -> 44747.975 | D18: =AVERAGEIFS(Cleaned_Data!$V$2:$V$4001,Cleaned_Data!$E$2:$E$4001,"Zaid") -> 44212.034
A19: Total Revenue (INR) | B19: =SUMIFS(Cleaned_Data!$X$2:$X$4001,Cleaned_Data!$E$2:$E$4001,"Kharif") -> 1264369200 | C19: =SUMIFS(Cleaned_Data!$X$2:$X$4001,Cleaned_Data!$E$2:$E$4001,"Rabi") -> 978682881 | D19: =SUMIFS(Cleaned_Data!$X$2:$X$4001,Cleaned_Data!$E$2:$E$4001,"Zaid") -> 308388111
A20: Total Cost (INR) | B20: =SUMIFS(Cleaned_Data!$W$2:$W$4001,Cleaned_Data!$E$2:$E$4001,"Kharif") -> 946080042 | C20: =SUMIFS(Cleaned_Data!$W$2:$W$4001,Cleaned_Data!$E$2:$E$4001,"Rabi") -> 836012113 | D20: =SUMIFS(Cleaned_Data!$W$2:$W$4001,Cleaned_Data!$E$2:$E$4001,"Zaid") -> 323122177
A21: Total Profit (INR) | B21: =SUMIFS(Cleaned_Data!$Y$2:$Y$4001,Cleaned_Data!$E$2:$E$4001,"Kharif") -> 318289158 | C21: =SUMIFS(Cleaned_Data!$Y$2:$Y$4001,Cleaned_Data!$E$2:$E$4001,"Rabi") -> 142670768 | D21: =SUMIFS(Cleaned_Data!$Y$2:$Y$4001,Cleaned_Data!$E$2:$E$4001,"Zaid") -> -14734066
A22: Avg Profit per Farm (INR) | B22: =AVERAGEIFS(Cleaned_Data!$Y$2:$Y$4001,Cleaned_Data!$E$2:$E$4001,"Kharif") -> 178914.65 | C22: =AVERAGEIFS(Cleaned_Data!$Y$2:$Y$4001,Cleaned_Data!$E$2:$E$4001,"Rabi") -> 87689.47 | D22: =AVERAGEIFS(Cleaned_Data!$Y$2:$Y$4001,Cleaned_Data!$E$2:$E$4001,"Zaid") -> -24804.825
A23: Profit Margin (%) | B23: =B21/B19 -> 0.25173751 | C23: =C21/C19 -> 0.14577834 | D23: =D21/D19 -> -0.047777672
A24: Avg Water Used (m3) | B24: =AVERAGEIFS(Cleaned_Data!$Z$2:$Z$4001,Cleaned_Data!$E$2:$E$4001,"Kharif") -> 6102.2012 | C24: =AVERAGEIFS(Cleaned_Data!$Z$2:$Z$4001,Cleaned_Data!$E$2:$E$4001,"Rabi") -> 5846.9871 | D24: =AVERAGEIFS(Cleaned_Data!$Z$2:$Z$4001,Cleaned_Data!$E$2:$E$4001,"Zaid") -> 6419.8939
A25: Avg Water Efficiency (t/1000m3) | B25: =AVERAGEIFS(Cleaned_Data!$AA$2:$AA$4001,Cleaned_Data!$E$2:$E$4001,"Kharif") -> 5.8918336 | C25: =AVERAGEIFS(Cleaned_Data!$AA$2:$AA$4001,Cleaned_Data!$E$2:$E$4001,"Rabi") -> 5.1861223 | D25: =AVERAGEIFS(Cleaned_Data!$AA$2:$AA$4001,Cleaned_Data!$E$2:$E$4001,"Zaid") -> 4.4132391
A26: Avg Disease/Pest Risk (%) | B26: =AVERAGEIFS(Cleaned_Data!$AB$2:$AB$4001,Cleaned_Data!$E$2:$E$4001,"Kharif") -> 54.467903 | C26: =AVERAGEIFS(Cleaned_Data!$AB$2:$AB$4001,Cleaned_Data!$E$2:$E$4001,"Rabi") -> 40.482114 | D26: =AVERAGEIFS(Cleaned_Data!$AB$2:$AB$4001,Cleaned_Data!$E$2:$E$4001,"Zaid") -> 38.216667
A27: Loss-Making Farms (%) | B27: =COUNTIFS(Cleaned_Data!$E$2:$E$4001,"Kharif",Cleaned_Data!$Y$2:$Y$4001,"<0")/COUNTIF(Cleaned_Data!$E$2:$E$4001,"Kharif") -> 0.42214727 | C27: =COUNTIFS(Cleaned_Data!$E$2:$E$4001,"Rabi",Cleaned_Data!$Y$2:$Y$4001,"<0")/COUNTIF(Cleaned_Data!$E$2:$E$4001,"Rabi") -> 0.51137062 | D27: =COUNTIFS(Cleaned_Data!$E$2:$E$4001,"Zaid",Cleaned_Data!$Y$2:$Y$4001,"<0")/COUNTIF(Cleaned_Data!$E$2:$E$4001,"Zaid") -> 0.64478114

Sheet Season_Crop_Matrix
A1: Average Yield & Profit by Season x Crop
A2: Checks whether seasonal patterns are consistent across crop types
A4: Avg Yield (t/ha)
A5: Crop | B5: Kharif | C5: Rabi | D5: Zaid
A6: Wheat | B6: =IFERROR(AVERAGEIFS(Cleaned_Data!$T$2:$T$4001,Cleaned_Data!$E$2:$E$4001,"Kharif",Cleaned_Data!$D$2:$D$4001,"Wheat"),"n/a") -> 2.2554452 | C6: =IFERROR(AVERAGEIFS(Cleaned_Data!$T$2:$T$4001,Cleaned_Data!$E$2:$E$4001,"Rabi",Cleaned_Data!$D$2:$D$4001,"Wheat"),"n/a") -> 2.0588186 | D6: =IFERROR(AVERAGEIFS(Cleaned_Data!$T$2:$T$4001,Cleaned_Data!$E$2:$E$4001,"Zaid",Cleaned_Data!$D$2:$D$4001,"Wheat"),"n/a") -> 1.7485882
A7: Rice | B7: =IFERROR(AVERAGEIFS(Cleaned_Data!$T$2:$T$4001,Cleaned_Data!$E$2:$E$4001,"Kharif",Cleaned_Data!$D$2:$D$4001,"Rice"),"n/a") -> 2.7076433 | C7: =IFERROR(AVERAGEIFS(Cleaned_Data!$T$2:$T$4001,Cleaned_Data!$E$2:$E$4001,"Rabi",Cleaned_Data!$D$2:$D$4001,"Rice"),"n/a") -> 2.3336131 | D7: =IFERROR(AVERAGEIFS(Cleaned_Data!$T$2:$T$4001,Cleaned_Data!$E$2:$E$4001,"Zaid",Cleaned_Data!$D$2:$D$4001,"Rice"),"n/a") -> 1.9004902
A8: Maize | B8: =IFERROR(AVERAGEIFS(Cleaned_Data!$T$2:$T$4001,Cleaned_Data!$E$2:$E$4001,"Kharif",Cleaned_Data!$D$2:$D$4001,"Maize"),"n/a") -> 2.9664103 | C8: =IFERROR(AVERAGEIFS(Cleaned_Data!$T$2:$T$4001,Cleaned_Data!$E$2:$E$4001,"Rabi",Cleaned_Data!$D$2:$D$4001,"Maize"),"n/a") -> 2.6148498 | D8: =IFERROR(AVERAGEIFS(Cleaned_Data!$T$2:$T$4001,Cleaned_Data!$E$2:$E$4001,"Zaid",Cleaned_Data!$D$2:$D$4001,"Maize"),"n/a") -> 2.297619
A9: Cotton | B9: =IFERROR(AVERAGEIFS(Cleaned_Data!$T$2:$T$4001,Cleaned_Data!$E$2:$E$4001,"Kharif",Cleaned_Data!$D$2:$D$4001,"Cotton"),"n/a") -> 1.372 | C9: =IFERROR(AVERAGEIFS(Cleaned_Data!$T$2:$T$4001,Cleaned_Data!$E$2:$E$4001,"Rabi",Cleaned_Data!$D$2:$D$4001,"Cotton"),"n/a") -> 1.1928856 | D9: =IFERROR(AVERAGEIFS(Cleaned_Data!$T$2:$T$4001,Cleaned_Data!$E$2:$E$4001,"Zaid",Cleaned_Data!$D$2:$D$4001,"Cotton"),"n/a") -> 0.95163043
A10: Pulses | B10: =IFERROR(AVERAGEIFS(Cleaned_Data!$T$2:$T$4001,Cleaned_Data!$E$2:$E$4001,"Kharif",Cleaned_Data!$D$2:$D$4001,"Pulses"),"n/a") -> 1.0360633 | C10: =IFERROR(AVERAGEIFS(Cleaned_Data!$T$2:$T$4001,Cleaned_Data!$E$2:$E$4001,"Rabi",Cleaned_Data!$D$2:$D$4001,"Pulses"),"n/a") -> 0.87187793 | D10: =IFERROR(AVERAGEIFS(Cleaned_Data!$T$2:$T$4001,Cleaned_Data!$E$2:$E$4001,"Zaid",Cleaned_Data!$D$2:$D$4001,"Pulses"),"n/a") -> 0.65209677
A11: Groundnut | B11: =IFERROR(AVERAGEIFS(Cleaned_Data!$T$2:$T$4001,Cleaned_Data!$E$2:$E$4001,"Kharif",Cleaned_Data!$D$2:$D$4001,"Groundnut"),"n/a") -> 1.4836269 | C11: =IFERROR(AVERAGEIFS(Cleaned_Data!$T$2:$T$4001,Cleaned_Data!$E$2:$E$4001,"Rabi",Cleaned_Data!$D$2:$D$4001,"Groundnut"),"n/a") -> 1.2214124 | D11: =IFERROR(AVERAGEIFS(Cleaned_Data!$T$2:$T$4001,Cleaned_Data!$E$2:$E$4001,"Zaid",Cleaned_Data!$D$2:$D$4001,"Groundnut"),"n/a") -> 1.0377778
A12: Chilli | B12: =IFERROR(AVERAGEIFS(Cleaned_Data!$T$2:$T$4001,Cleaned_Data!$E$2:$E$4001,"Kharif",Cleaned_Data!$D$2:$D$4001,"Chilli"),"n/a") -> 1.7314054 | C12: =IFERROR(AVERAGEIFS(Cleaned_Data!$T$2:$T$4001,Cleaned_Data!$E$2:$E$4001,"Rabi",Cleaned_Data!$D$2:$D$4001,"Chilli"),"n/a") -> 1.4615951 | D12: =IFERROR(AVERAGEIFS(Cleaned_Data!$T$2:$T$4001,Cleaned_Data!$E$2:$E$4001,"Zaid",Cleaned_Data!$D$2:$D$4001,"Chilli"),"n/a") -> 1.1778125
A13: Sugarcane | B13: =IFERROR(AVERAGEIFS(Cleaned_Data!$T$2:$T$4001,Cleaned_Data!$E$2:$E$4001,"Kharif",Cleaned_Data!$D$2:$D$4001,"Sugarcane"),"n/a") -> 53.45912 | C13: =IFERROR(AVERAGEIFS(Cleaned_Data!$T$2:$T$4001,Cleaned_Data!$E$2:$E$4001,"Rabi",Cleaned_Data!$D$2:$D$4001,"Sugarcane"),"n/a") -> 43.940388 | D13: =IFERROR(AVERAGEIFS(Cleaned_Data!$T$2:$T$4001,Cleaned_Data!$E$2:$E$4001,"Zaid",Cleaned_Data!$D$2:$D$4001,"Sugarcane"),"n/a") -> 38.423922
A16: Avg Profit per Farm (INR)
A17: Crop | B17: Kharif | C17: Rabi | D17: Zaid
A18: Wheat | B18: =IFERROR(AVERAGEIFS(Cleaned_Data!$Y$2:$Y$4001,Cleaned_Data!$E$2:$E$4001,"Kharif",Cleaned_Data!$D$2:$D$4001,"Wheat"),"n/a") -> -105871.87 | C18: =IFERROR(AVERAGEIFS(Cleaned_Data!$Y$2:$Y$4001,Cleaned_Data!$E$2:$E$4001,"Rabi",Cleaned_Data!$D$2:$D$4001,"Wheat"),"n/a") -> -119954.57 | D18: =IFERROR(AVERAGEIFS(Cleaned_Data!$Y$2:$Y$4001,Cleaned_Data!$E$2:$E$4001,"Zaid",Cleaned_Data!$D$2:$D$4001,"Wheat"),"n/a") -> -193208.95
A19: Rice | B19: =IFERROR(AVERAGEIFS(Cleaned_Data!$Y$2:$Y$4001,Cleaned_Data!$E$2:$E$4001,"Kharif",Cleaned_Data!$D$2:$D$4001,"Rice"),"n/a") -> -64903.404 | C19: =IFERROR(AVERAGEIFS(Cleaned_Data!$Y$2:$Y$4001,Cleaned_Data!$E$2:$E$4001,"Rabi",Cleaned_Data!$D$2:$D$4001,"Rice"),"n/a") -> -98427.869 | D19: =IFERROR(AVERAGEIFS(Cleaned_Data!$Y$2:$Y$4001,Cleaned_Data!$E$2:$E$4001,"Zaid",Cleaned_Data!$D$2:$D$4001,"Rice"),"n/a") -> -227239.34
A20: Maize | B20: =IFERROR(AVERAGEIFS(Cleaned_Data!$Y$2:$Y$4001,Cleaned_Data!$E$2:$E$4001,"Kharif",Cleaned_Data!$D$2:$D$4001,"Maize"),"n/a") -> -39332.671 | C20: =IFERROR(AVERAGEIFS(Cleaned_Data!$Y$2:$Y$4001,Cleaned_Data!$E$2:$E$4001,"Rabi",Cleaned_Data!$D$2:$D$4001,"Maize"),"n/a") -> -89133.403 | D20: =IFERROR(AVERAGEIFS(Cleaned_Data!$Y$2:$Y$4001,Cleaned_Data!$E$2:$E$4001,"Zaid",Cleaned_Data!$D$2:$D$4001,"Maize"),"n/a") -> -194049.17
A21: Cotton | B21: =IFERROR(AVERAGEIFS(Cleaned_Data!$Y$2:$Y$4001,Cleaned_Data!$E$2:$E$4001,"Kharif",Cleaned_Data!$D$2:$D$4001,"Cotton"),"n/a") -> 216999.55 | C21: =IFERROR(AVERAGEIFS(Cleaned_Data!$Y$2:$Y$4001,Cleaned_Data!$E$2:$E$4001,"Rabi",Cleaned_Data!$D$2:$D$4001,"Cotton"),"n/a") -> 107343.59 | D21: =IFERROR(AVERAGEIFS(Cleaned_Data!$Y$2:$Y$4001,Cleaned_Data!$E$2:$E$4001,"Zaid",Cleaned_Data!$D$2:$D$4001,"Cotton"),"n/a") -> -53925.337
A22: Pulses | B22: =IFERROR(AVERAGEIFS(Cleaned_Data!$Y$2:$Y$4001,Cleaned_Data!$E$2:$E$4001,"Kharif",Cleaned_Data!$D$2:$D$4001,"Pulses"),"n/a") -> 43338.896 | C22: =IFERROR(AVERAGEIFS(Cleaned_Data!$Y$2:$Y$4001,Cleaned_Data!$E$2:$E$4001,"Rabi",Cleaned_Data!$D$2:$D$4001,"Pulses"),"n/a") -> -14309.136 | D22: =IFERROR(AVERAGEIFS(Cleaned_Data!$Y$2:$Y$4001,Cleaned_Data!$E$2:$E$4001,"Zaid",Cleaned_Data!$D$2:$D$4001,"Pulses"),"n/a") -> -139227.81
A23: Groundnut | B23: =IFERROR(AVERAGEIFS(Cleaned_Data!$Y$2:$Y$4001,Cleaned_Data!$E$2:$E$4001,"Kharif",Cleaned_Data!$D$2:$D$4001,"Groundnut"),"n/a") -> 108265.44 | C23: =IFERROR(AVERAGEIFS(Cleaned_Data!$Y$2:$Y$4001,Cleaned_Data!$E$2:$E$4001,"Rabi",Cleaned_Data!$D$2:$D$4001,"Groundnut"),"n/a") -> 10416.542 | D23: =IFERROR(AVERAGEIFS(Cleaned_Data!$Y$2:$Y$4001,Cleaned_Data!$E$2:$E$4001,"Zaid",Cleaned_Data!$D$2:$D$4001,"Groundnut"),"n/a") -> -68872.5
A24: Chilli | B24: =IFERROR(AVERAGEIFS(Cleaned_Data!$Y$2:$Y$4001,Cleaned_Data!$E$2:$E$4001,"Kharif",Cleaned_Data!$D$2:$D$4001,"Chilli"),"n/a") -> 954380.42 | C24: =IFERROR(AVERAGEIFS(Cleaned_Data!$Y$2:$Y$4001,Cleaned_Data!$E$2:$E$4001,"Rabi",Cleaned_Data!$D$2:$D$4001,"Chilli"),"n/a") -> 638572.5 | D24: =IFERROR(AVERAGEIFS(Cleaned_Data!$Y$2:$Y$4001,Cleaned_Data!$E$2:$E$4001,"Zaid",Cleaned_Data!$D$2:$D$4001,"Chilli"),"n/a") -> 448659.09
A25: Sugarcane | B25: =IFERROR(AVERAGEIFS(Cleaned_Data!$Y$2:$Y$4001,Cleaned_Data!$E$2:$E$4001,"Kharif",Cleaned_Data!$D$2:$D$4001,"Sugarcane"),"n/a") -> 1000790.8 | C25: =IFERROR(AVERAGEIFS(Cleaned_Data!$Y$2:$Y$4001,Cleaned_Data!$E$2:$E$4001,"Rabi",Cleaned_Data!$D$2:$D$4001,"Sugarcane"),"n/a") -> 731612.86 | D25: =IFERROR(AVERAGEIFS(Cleaned_Data!$Y$2:$Y$4001,Cleaned_Data!$E$2:$E$4001,"Zaid",Cleaned_Data!$D$2:$D$4001,"Sugarcane"),"n/a") -> 583635.8

Sheet Season_State_Matrix
A1: Average Yield by Season x State
A2: Checks whether seasonal yield patterns are consistent across regions
A4: State | B4: Kharif | C4: Rabi | D4: Zaid
A5: Andhra Pradesh | B5: =IFERROR(AVERAGEIFS(Cleaned_Data!$T$2:$T$4001,Cleaned_Data!$E$2:$E$4001,"Kharif",Cleaned_Data!$B$2:$B$4001,"Andhra Pradesh"),"n/a") -> 5.681 | C5: =IFERROR(AVERAGEIFS(Cleaned_Data!$T$2:$T$4001,Cleaned_Data!$E$2:$E$4001,"Rabi",Cleaned_Data!$B$2:$B$4001,"Andhra Pradesh"),"n/a") -> 3.4670098 | D5: =IFERROR(AVERAGEIFS(Cleaned_Data!$T$2:$T$4001,Cleaned_Data!$E$2:$E$4001,"Zaid",Cleaned_Data!$B$2:$B$4001,"Andhra Pradesh"),"n/a") -> 4.4414118
A6: Telangana | B6: =IFERROR(AVERAGEIFS(Cleaned_Data!$T$2:$T$4001,Cleaned_Data!$E$2:$E$4001,"Kharif",Cleaned_Data!$B$2:$B$4001,"Telangana"),"n/a") -> 5.5516667 | C6: =IFERROR(AVERAGEIFS(Cleaned_Data!$T$2:$T$4001,Cleaned_Data!$E$2:$E$4001,"Rabi",Cleaned_Data!$B$2:$B$4001,"Telangana"),"n/a") -> 4.7963959 | D6: =IFERROR(AVERAGEIFS(Cleaned_Data!$T$2:$T$4001,Cleaned_Data!$E$2:$E$4001,"Zaid",Cleaned_Data!$B$2:$B$4001,"Telangana"),"n/a") -> 4.2418824
A7: Maharashtra | B7: =IFERROR(AVERAGEIFS(Cleaned_Data!$T$2:$T$4001,Cleaned_Data!$E$2:$E$4001,"Kharif",Cleaned_Data!$B$2:$B$4001,"Maharashtra"),"n/a") -> 5.4326577 | C7: =IFERROR(AVERAGEIFS(Cleaned_Data!$T$2:$T$4001,Cleaned_Data!$E$2:$E$4001,"Rabi",Cleaned_Data!$B$2:$B$4001,"Maharashtra"),"n/a") -> 5.5019266 | D7: =IFERROR(AVERAGEIFS(Cleaned_Data!$T$2:$T$4001,Cleaned_Data!$E$2:$E$4001,"Zaid",Cleaned_Data!$B$2:$B$4001,"Maharashtra"),"n/a") -> 2.2668056
A8: Madhya Pradesh | B8: =IFERROR(AVERAGEIFS(Cleaned_Data!$T$2:$T$4001,Cleaned_Data!$E$2:$E$4001,"Kharif",Cleaned_Data!$B$2:$B$4001,"Madhya Pradesh"),"n/a") -> 5.9895575 | C8: =IFERROR(AVERAGEIFS(Cleaned_Data!$T$2:$T$4001,Cleaned_Data!$E$2:$E$4001,"Rabi",Cleaned_Data!$B$2:$B$4001,"Madhya Pradesh"),"n/a") -> 3.7607692 | D8: =IFERROR(AVERAGEIFS(Cleaned_Data!$T$2:$T$4001,Cleaned_Data!$E$2:$E$4001,"Zaid",Cleaned_Data!$B$2:$B$4001,"Madhya Pradesh"),"n/a") -> 5.4615873
A9: Karnataka | B9: =IFERROR(AVERAGEIFS(Cleaned_Data!$T$2:$T$4001,Cleaned_Data!$E$2:$E$4001,"Kharif",Cleaned_Data!$B$2:$B$4001,"Karnataka"),"n/a") -> 6.4566507 | C9: =IFERROR(AVERAGEIFS(Cleaned_Data!$T$2:$T$4001,Cleaned_Data!$E$2:$E$4001,"Rabi",Cleaned_Data!$B$2:$B$4001,"Karnataka"),"n/a") -> 4.7730583 | D9: =IFERROR(AVERAGEIFS(Cleaned_Data!$T$2:$T$4001,Cleaned_Data!$E$2:$E$4001,"Zaid",Cleaned_Data!$B$2:$B$4001,"Karnataka"),"n/a") -> 6.6232432
A10: Gujarat | B10: =IFERROR(AVERAGEIFS(Cleaned_Data!$T$2:$T$4001,Cleaned_Data!$E$2:$E$4001,"Kharif",Cleaned_Data!$B$2:$B$4001,"Gujarat"),"n/a") -> 6.3384163 | C10: =IFERROR(AVERAGEIFS(Cleaned_Data!$T$2:$T$4001,Cleaned_Data!$E$2:$E$4001,"Rabi",Cleaned_Data!$B$2:$B$4001,"Gujarat"),"n/a") -> 5.65725 | D10: =IFERROR(AVERAGEIFS(Cleaned_Data!$T$2:$T$4001,Cleaned_Data!$E$2:$E$4001,"Zaid",Cleaned_Data!$B$2:$B$4001,"Gujarat"),"n/a") -> 4.0750746
A11: Tamil Nadu | B11: =IFERROR(AVERAGEIFS(Cleaned_Data!$T$2:$T$4001,Cleaned_Data!$E$2:$E$4001,"Kharif",Cleaned_Data!$B$2:$B$4001,"Tamil Nadu"),"n/a") -> 5.520534 | C11: =IFERROR(AVERAGEIFS(Cleaned_Data!$T$2:$T$4001,Cleaned_Data!$E$2:$E$4001,"Rabi",Cleaned_Data!$B$2:$B$4001,"Tamil Nadu"),"n/a") -> 4.4950481 | D11: =IFERROR(AVERAGEIFS(Cleaned_Data!$T$2:$T$4001,Cleaned_Data!$E$2:$E$4001,"Zaid",Cleaned_Data!$B$2:$B$4001,"Tamil Nadu"),"n/a") -> 4.0977465
A12: Punjab | B12: =IFERROR(AVERAGEIFS(Cleaned_Data!$T$2:$T$4001,Cleaned_Data!$E$2:$E$4001,"Kharif",Cleaned_Data!$B$2:$B$4001,"Punjab"),"n/a") -> 4.1006335 | C12: =IFERROR(AVERAGEIFS(Cleaned_Data!$T$2:$T$4001,Cleaned_Data!$E$2:$E$4001,"Rabi",Cleaned_Data!$B$2:$B$4001,"Punjab"),"n/a") -> 8.6093548 | D12: =IFERROR(AVERAGEIFS(Cleaned_Data!$T$2:$T$4001,Cleaned_Data!$E$2:$E$4001,"Zaid",Cleaned_Data!$B$2:$B$4001,"Punjab"),"n/a") -> 5.9096104

Sheet Irrigation_Analysis
A1: Irrigation Method Usage & Efficiency by Season
A4: Farm Count
A5: Irrigation Method | B5: Kharif | C5: Rabi | D5: Zaid | F5: Total
A6: Drip | B6: =COUNTIFS(Cleaned_Data!$E$2:$E$4001,"Kharif",Cleaned_Data!$P$2:$P$4001,"Drip") -> 405 | C6: =COUNTIFS(Cleaned_Data!$E$2:$E$4001,"Rabi",Cleaned_Data!$P$2:$P$4001,"Drip") -> 370 | D6: =COUNTIFS(Cleaned_Data!$E$2:$E$4001,"Zaid",Cleaned_Data!$P$2:$P$4001,"Drip") -> 140 | F6: =SUM(B6:D6) -> 915
A7: Flood | B7: =COUNTIFS(Cleaned_Data!$E$2:$E$4001,"Kharif",Cleaned_Data!$P$2:$P$4001,"Flood") -> 590 | C7: =COUNTIFS(Cleaned_Data!$E$2:$E$4001,"Rabi",Cleaned_Data!$P$2:$P$4001,"Flood") -> 526 | D7: =COUNTIFS(Cleaned_Data!$E$2:$E$4001,"Zaid",Cleaned_Data!$P$2:$P$4001,"Flood") -> 194 | F7: =SUM(B7:D7) -> 1310
A8: Rainfed | B8: =COUNTIFS(Cleaned_Data!$E$2:$E$4001,"Kharif",Cleaned_Data!$P$2:$P$4001,"Rainfed") -> 463 | C8: =COUNTIFS(Cleaned_Data!$E$2:$E$4001,"Rabi",Cleaned_Data!$P$2:$P$4001,"Rainfed") -> 438 | D8: =COUNTIFS(Cleaned_Data!$E$2:$E$4001,"Zaid",Cleaned_Data!$P$2:$P$4001,"Rainfed") -> 140 | F8: =SUM(B8:D8) -> 1041
A9: Sprinkler | B9: =COUNTIFS(Cleaned_Data!$E$2:$E$4001,"Kharif",Cleaned_Data!$P$2:$P$4001,"Sprinkler") -> 321 | C9: =COUNTIFS(Cleaned_Data!$E$2:$E$4001,"Rabi",Cleaned_Data!$P$2:$P$4001,"Sprinkler") -> 293 | D9: =COUNTIFS(Cleaned_Data!$E$2:$E$4001,"Zaid",Cleaned_Data!$P$2:$P$4001,"Sprinkler") -> 120 | F9: =SUM(B9:D9) -> 734
A12: Avg Water Efficiency (t/1000m3)
A13: Irrigation Method | B13: Kharif | C13: Rabi | D13: Zaid
A14: Drip | B14: =IFERROR(AVERAGEIFS(Cleaned_Data!$AA$2:$AA$4001,Cleaned_Data!$E$2:$E$4001,"Kharif",Cleaned_Data!$P$2:$P$4001,"Drip"),"n/a") -> 6.8038173 | C14: =IFERROR(AVERAGEIFS(Cleaned_Data!$AA$2:$AA$4001,Cleaned_Data!$E$2:$E$4001,"Rabi",Cleaned_Data!$P$2:$P$4001,"Drip"),"n/a") -> 6.0471568 | D14: =IFERROR(AVERAGEIFS(Cleaned_Data!$AA$2:$AA$4001,Cleaned_Data!$E$2:$E$4001,"Zaid",Cleaned_Data!$P$2:$P$4001,"Drip"),"n/a") -> 5.2959214
A15: Flood | B15: =IFERROR(AVERAGEIFS(Cleaned_Data!$AA$2:$AA$4001,Cleaned_Data!$E$2:$E$4001,"Kharif",Cleaned_Data!$P$2:$P$4001,"Flood"),"n/a") -> 3.6371559 | C15: =IFERROR(AVERAGEIFS(Cleaned_Data!$AA$2:$AA$4001,Cleaned_Data!$E$2:$E$4001,"Rabi",Cleaned_Data!$P$2:$P$4001,"Flood"),"n/a") -> 3.4776901 | D15: =IFERROR(AVERAGEIFS(Cleaned_Data!$AA$2:$AA$4001,Cleaned_Data!$E$2:$E$4001,"Zaid",Cleaned_Data!$P$2:$P$4001,"Flood"),"n/a") -> 2.7304691
A16: Rainfed | B16: =IFERROR(AVERAGEIFS(Cleaned_Data!$AA$2:$AA$4001,Cleaned_Data!$E$2:$E$4001,"Kharif",Cleaned_Data!$P$2:$P$4001,"Rainfed"),"n/a") -> 8.8475918 | C16: =IFERROR(AVERAGEIFS(Cleaned_Data!$AA$2:$AA$4001,Cleaned_Data!$E$2:$E$4001,"Rabi",Cleaned_Data!$P$2:$P$4001,"Rainfed"),"n/a") -> 6.8729406 | D16: =IFERROR(AVERAGEIFS(Cleaned_Data!$AA$2:$AA$4001,Cleaned_Data!$E$2:$E$4001,"Zaid",Cleaned_Data!$P$2:$P$4001,"Rainfed"),"n/a") -> 5.4794
A17: Sprinkler | B17: =IFERROR(AVERAGEIFS(Cleaned_Data!$AA$2:$AA$4001,Cleaned_Data!$E$2:$E$4001,"Kharif",Cleaned_Data!$P$2:$P$4001,"Sprinkler"),"n/a") -> 4.6220218 | C17: =IFERROR(AVERAGEIFS(Cleaned_Data!$AA$2:$AA$4001,Cleaned_Data!$E$2:$E$4001,"Rabi",Cleaned_Data!$P$2:$P$4001,"Sprinkler"),"n/a") -> 4.6442321 | D17: =IFERROR(AVERAGEIFS(Cleaned_Data!$AA$2:$AA$4001,Cleaned_Data!$E$2:$E$4001,"Zaid",Cleaned_Data!$P$2:$P$4001,"Sprinkler"),"n/a") -> 4.8600667

Sheet Correlation_Analysis
A1: Correlation Analysis
A2: Pearson correlation coefficients across all 4,000 cleaned records (-1 to +1)
A3: Values near +1/-1 indicate a strong relationship; near 0 indicates little/no linear relationship.
A5: Variable Pair | B5: Correlation (r)
A6: Rainfall vs Yield | B6: =ROUND(CORREL(Cleaned_Data!$G$2:$G$4001,Cleaned_Data!$T$2:$T$4001),3) -> 0.027
A7: Temperature vs Yield | B7: =ROUND(CORREL(Cleaned_Data!$H$2:$H$4001,Cleaned_Data!$T$2:$T$4001),3) -> 0.009
A8: Soil Moisture vs Yield | B8: =ROUND(CORREL(Cleaned_Data!$L$2:$L$4001,Cleaned_Data!$T$2:$T$4001),3) -> 0.01
A9: Fertilizer vs Yield | B9: =ROUND(CORREL(Cleaned_Data!$Q$2:$Q$4001,Cleaned_Data!$T$2:$T$4001),3) -> 0
A10: Seed Quality vs Yield | B10: =ROUND(CORREL(Cleaned_Data!$S$2:$S$4001,Cleaned_Data!$T$2:$T$4001),3) -> -0.008
A11: Disease/Pest Risk vs Yield | B11: =ROUND(CORREL(Cleaned_Data!$AB$2:$AB$4001,Cleaned_Data!$T$2:$T$4001),3) -> 0.013
A12: Water Used vs Yield | B12: =ROUND(CORREL(Cleaned_Data!$Z$2:$Z$4001,Cleaned_Data!$T$2:$T$4001),3) -> 0.387
A13: Water Efficiency vs Profit | B13: =ROUND(CORREL(Cleaned_Data!$AA$2:$AA$4001,Cleaned_Data!$Y$2:$Y$4001),3) -> 0.489
A14: Total Cost vs Profit | B14: =ROUND(CORREL(Cleaned_Data!$W$2:$W$4001,Cleaned_Data!$Y$2:$Y$4001),3) -> 0.068
A15: Market Price vs Profit | B15: =ROUND(CORREL(Cleaned_Data!$V$2:$V$4001,Cleaned_Data!$Y$2:$Y$4001),3) -> 0.225
A16: Yield vs Profit | B16: =ROUND(CORREL(Cleaned_Data!$T$2:$T$4001,Cleaned_Data!$Y$2:$Y$4001),3) -> 0.489
A17: Fertilizer vs Disease/Pest Risk | B17: =ROUND(CORREL(Cleaned_Data!$Q$2:$Q$4001,Cleaned_Data!$AB$2:$AB$4001),3) -> 0.018

Sheet Charts
A1: Seasonal Agriculture Performance — Charts
A2: All charts reference live formulas in Season_Summary / Season_Crop_Matrix / Irrigation_Analysis — they update automatically if the underlying data changes.

Sheet Key_Insights_Recommendations
A1: Key Insights & Recommendations
A2: Findings below are drawn directly from the Season_Summary, Season_Crop_Matrix, Season_State_Matrix and Correlation_Analysis sheets.
A4: 1. How does agricultural performance vary across seasons?
A5: • Kharif has the most farms (1,779), the highest average yield (~5.63 t/ha) and by far the highest total profit (~INR 318 million). Rabi is close behind on yield (~5.09 t/ha) with a smaller but positive total profit (~INR 143 million). Zaid is the weakest season: lowest yield (~4.64 t/ha) and the ONLY season with a negative total profit (see Season_Summary, row 'Total Profit (INR)').
A7: 2. What major seasonal patterns can be observed?
A8: • Rainfall, humidity and soil moisture all fall steadily from Kharif -> Rabi -> Zaid (as expected, since Kharif is the monsoon season). Sunlight hours rise in the same order. Fertilizer, pesticide and seed-quality inputs are almost identical across seasons — input levels are not what's driving the yield gap.
A10: 3. Which characteristics change between seasons, and which stay stable?
A11: • Change a lot: rainfall (852 -> 436 -> 299 mm), humidity (72% -> 58% -> 52%), soil moisture (31% -> 24% -> 19%), disease/pest risk (54% -> 40% -> 38%).
A12: • Stay stable: fertilizer use (~185-187 kg/ha), pesticide use (~5.0-5.2 L/ha), seed quality (~0.82-0.83), average farm area (~7.8-8.1 ha) and market price (~INR 44,200-44,850/tonne).
A14: 4. Are there noticeable differences/variations in resource usage across seasons?
A15: • Input resources (fertilizer, pesticide, seed quality) are essentially flat across seasons — the variation is almost entirely on the environmental side (rainfall, humidity, soil moisture) and in water usage efficiency, which drops from 5.89 t/1000m3 in Kharif to 4.41 t/1000m3 in Zaid.
A17: 5. Are there relationships between seasonal environmental conditions and performance?
... A39: → Carry these findings into the Python/Jupyter phase: run significance tests (ANOVA/t-tests) on the season differences, and a multi-variable regression to isolate which factors truly drive yield once correlated variables (e.g. water use, season, crop) are controlled for simultaneously.
